Workbook

Sheet 2021 reale
B1: ELENCO FATTURE
B2: Anno 2021 | M2: Anno 2017
B4: Nr | C4: Anno | D4: Trimestre | F4: Data emissione | G4: Pagamento (gg) | H4: Data Scadenza | I4: Data pagamento | J4: Incassato | K4: Destinatario | L4: Netto | M4: Iva | N4: Integr. 4% | O4: Bollo | P4: Totale | Q4: Estero | W4: Ferie | X4: Extra Alessandro | Y4: Fattura reale | Z4: Fattura stimata
A5: 1 | E5: =IF(#REF!="CASA",CONCATENATE("C:\Users\studi\Google Drive\CONTABILITA'\",C5,"\",D5," Trimestre\Fatture\",B5,".pdf"),CONCATENATE("C:\Users\Sebastiano\Google Drive\CONTABILITA'\",C5,"\",D5," Trimestre\Fatture\",B5,".pdf")) -> #REF! | F5: 44227 | G5: 5 | H5: =EOMONTH(F5,0)+G5 -> 44232 | J5: x | K5: Alessandro | L5: =IF($U$7>=A5,IF(Y5="",Z5,Y5),0)+X5 -> 5587 | M5: 0 | N5: =IF(Q5="x",0,0.04*L5) -> 223.48 | O5: 0 | P5: =L5+N5+O5 -> 5810.48 | X5: 3737 | Y5: 1850 | Z5: =(AH5-W5)*$T$9*$T$8 -> 1785 | AA5: =Y5/Z5 -> 1.0364146 | AF5: 44197 | AG5: =AF6-1 -> 44227 | AH5: =NETWORKDAYS(AF5,AG5) -> 21
A6: 2 | E6: =IF(#REF!="CASA",CONCATENATE("C:\Users\studi\Google Drive\CONTABILITA'\2019\",D6," Trimestre\Fatture\",B6,".pdf"),CONCATENATE("C:\Users\Sebastiano\Google Drive\CONTABILITA'\2019\",D6," Trimestre\Fatture\",B6,".pdf")) -> #REF! | F6: 44255 | G6: 5 | H6: =EOMONTH(F6,0)+G6 -> 44260 | J6: x | K6: Alessandro | L6: =IF($U$7>=A6,IF(Y6="",Z6,Y6),0)+X6 -> 5260 | M6: 0 | N6: =IF(Q6="x",0,0.04*L6) -> 210.4 | O6: 0 | P6: =L6+N6+O6 -> 5470.4 | T6: Precedenti | U6: Attuali | X6: 3500 | Y6: 1760 | Z6: =(AH6-W6)*$T$9*$T$8 -> 1700 | AA6: =Y6/Z6 -> 1.0352941 | AF6: 44228 | AG6: =AF7-1 -> 44255 | AH6: =NETWORKDAYS(AF6,AG6) -> 20
A7: 3 | E7: =IF(#REF!="CASA",CONCATENATE("C:\Users\studi\Google Drive\CONTABILITA'\2019\",D7," Trimestre\Fatture\",B7,".pdf"),CONCATENATE("C:\Users\Sebastiano\Google Drive\CONTABILITA'\2019\",D7," Trimestre\Fatture\",B7,".pdf")) -> #REF! | F7: 44286 | G7: 5 | H7: =EOMONTH(F7,0)+G7 -> 44291 | J7: x | K7: Alessandro | L7: =IF($U$7>=A7,IF(Y7="",Z7,Y7),0)+X7 -> 2005 | M7: 0 | N7: =IF(Q7="x",0,0.04*L7) -> 80.2 | O7: 0 | P7: =L7+N7+O7 -> 2085.2 | S7: Mesi | T7: 5 | U7: 12 | Y7: 2005 | Z7: =(AH7-W7)*$T$9*$T$8 -> 1955 | AA7: =Y7/Z7 -> 1.0255754 | AF7: 44256 | AG7: =AF8-1 -> 44286 | AH7: =NETWORKDAYS(AF7,AG7) -> 23
A8: 4 | E8: =IF(#REF!="CASA",CONCATENATE("C:\Users\studi\Google Drive\CONTABILITA'\2020\",D8," Trimestre\Fatture\",B8,".pdf"),CONCATENATE("C:\Users\Sebastiano\Google Drive\CONTABILITA'\2020\",D8," Trimestre\Fatture\",B8,".pdf")) -> #REF! | F8: 44316 | G8: 5 | H8: =EOMONTH(F8,0)+G8 -> 44321 | J8: x | K8: Alessandro | L8: =IF($U$7>=A8,IF(Y8="",Z8,Y8),0)+X8 -> 2020 | M8: 0 | N8: =IF(Q8="x",0,0.04*L8) -> 80.8 | O8: 0 | P8: =L8+N8+O8 -> 2100.8 | T8: 10 | Y8: 2020 | Z8: =(AH8-W8+2)*$T$9*$T$8 -> 2040 | AF8: 44287 | AG8: =AF9-1 -> 44316 | AH8: =NETWORKDAYS(AF8,AG8) -> 22
A9: 5 | E9: =IF(#REF!="CASA",CONCATENATE("C:\Users\studi\Google Drive\CONTABILITA'\2020\Fatture\",D9," Trimestre\",B9,".pdf"),CONCATENATE("C:\Users\Sebastiano\Google Drive\CONTABILITA'\2020\Fatture\",D9," Trimestre\",B9,".pdf")) -> #REF! | F9: 44347 | G9: 5 | H9: =EOMONTH(F9,0)+G9 -> 44352 | J9: x | K9: STI | L9: 2500 | M9: 0 | N9: 0 | O9: 2 | P9: =L9+N9+O9 -> 2502 | Q9: x | S9: Ore | T9: 8.5 | Y9: 2502 | Z9: 2500 | AF9: 44317 | AG9: =AF11-1 -> 44347 | AH9: =NETWORKDAYS(AF9,AG9) -> 21
A10: 6 | F10: 44376 | G10: 4 | H10: =EOMONTH(F10,0)+G10 -> 44381 | J10: x | K10: STI | L10: =IF($U$7>=A10,IF(Y10="",Z10,Y10),0)+X10 -> 1400 | M10: 0 | N10: =IF(Q10="x",0,0.04*L10) -> 0 | O10: 2 | P10: =L10+N10+O10 -> 1402 | Q10: x | Y10: 1400 | Z10: 1400
A11: 7 | E11: =IF(#REF!="CASA",CONCATENATE("C:\Users\studi\Google Drive\CONTABILITA'\2020\Fatture\",D11," Trimestre\",B11,".pdf"),CONCATENATE("C:\Users\Sebastiano\Google Drive\CONTABILITA'\2020\Fatture\",D11," Trimestre\",B11,".pdf")) -> #REF! | F11: 44377 | G11: 5 | H11: =EOMONTH(F11,0)+G11 -> 44382 | J11: x | K11: STI | L11: 1100 | M11: 0 | N11: =IF(Q11="x",0,0.04*L11) -> 44 | O11: 2 | P11: =L11+N11+O11 -> 1146 | S11: Giorni | T11: 21.5 | U11: =T11*T9 -> 182.75 | Y11: 1550 | Z11: 1100 | AF11: 44348 | AG11: =AF12-1 -> 44377 | AH11: =NETWORKDAYS(AF11,AG11) -> 22
A12: 8 | E12: =IF(#REF!="CASA",CONCATENATE("C:\Users\studi\Google Drive\CONTABILITA'\2020\Fatture\",D12," Trimestre\",B12,".pdf"),CONCATENATE("C:\Users\Sebastiano\Google Drive\CONTABILITA'\2020\Fatture\",D12," Trimestre\",B12,".pdf")) -> #REF! | F12: 44408 | G12: 5 | H12: =EOMONTH(F12,0)+G12 -> 44413 | J12: x | K12: STI | L12: 2500 | M12: 0 | N12: =IF(Q12="x",0,0.04*L12) -> 0 | O12: 2 | P12: =L12+N12+O12 -> 2502 | Q12: x | S12: Mensile | T12: =+T11*T9*T8 -> 1827.5 | Y12: 1550 | Z12: 2500 | AF12: 44378 | AG12: =AF13-1 -> 44408 | AH12: =NETWORKDAYS(AF12,AG12) -> 22
A13: 9 | E13: =IF(#REF!="CASA",CONCATENATE("C:\Users\studi\Google Drive\CONTABILITA'\2020\Fatture\",D13," Trimestre\",B13,".pdf"),CONCATENATE("C:\Users\Sebastiano\Google Drive\CONTABILITA'\2020\Fatture\",D13," Trimestre\",B13,".pdf")) -> #REF! | F13: 44439 | G13: 5 | H13: =EOMONTH(F13,0)+G13 -> 44444 | J13: x | K13: STI | L13: =IF($U$7>=A13,IF(Y13="",Z13,Y13),0)+X13 -> 2500 | M13: 0 | N13: =IF(Q13="x",0,0.04*L13) -> 0 | O13: 2 | P13: =L13+N13+O13 -> 2502 | Q13: x | Y13: 2500 | Z13: 2500 | AF13: 44409 | AG13: =AF14-1 -> 44439 | AH13: =NETWORKDAYS(AF13,AG13) -> 22
A14: 10 | E14: =IF(#REF!="CASA",CONCATENATE("C:\Users\studi\Google Drive\CONTABILITA'\2020\Fatture\",D14," Trimestre\",B14,".pdf"),CONCATENATE("C:\Users\Sebastiano\Google Drive\CONTABILITA'\2020\Fatture\",D14," Trimestre\",B14,".pdf")) -> #REF! | F14: 44469 | G14: 5 | H14: =EOMONTH(F14,0)+G14 -> 44474 | J14: x | K14: STI | L14: =IF($U$7>=A14,IF(Y14="",Z14,Y14),0)+X14 -> 2800 | M14: 0 | N14: =IF(Q14="x",0,0.04*L14) -> 0 | O14: 2 | P14: =L14+N14+O14 -> 2802 | Q14: x | T14: Coefficiente ATECO | U14: 0.78 | Y14: 2800 | Z14: 2500 | AF14: 44440 | AG14: =AF15-1 -> 44469 | AH14: =NETWORKDAYS(AF14,AG14) -> 22
A15: 11 | E15: =IF(#REF!="CASA",CONCATENATE("C:\Users\studi\Google Drive\CONTABILITA'\2020\Fatture\",D15," Trimestre\",B15,".pdf"),CONCATENATE("C:\Users\Sebastiano\Google Drive\CONTABILITA'\2020\Fatture\",D15," Trimestre\",B15,".pdf")) -> #REF! | F15: 44500 | G15: 5 | H15: =EOMONTH(F15,0)+G15 -> 44505 | J15: x | K15: STI | L15: 1550 | M15: 0 | N15: =IF(Q15="x",0,0.04*L15) -> 0 | O15: 2 | P15: =L15+N15+O15 -> 1552 | Q15: x | Y15: 3100 | Z15: 2500 | AF15: 44470 | AG15: =AF16-1 -> 44500 | AH15: =NETWORKDAYS(AF15,AG15) -> 21
A16: 12 | E16: =IF(#REF!="CASA",CONCATENATE("C:\Users\studi\Google Drive\CONTABILITA'\2020\Fatture\",D16," Trimestre\",B16,".pdf"),CONCATENATE("C:\Users\Sebastiano\Google Drive\CONTABILITA'\2020\Fatture\",D16," Trimestre\",B16,".pdf")) -> #REF! | F16: 44500 | G16: 5 | H16: =EOMONTH(F16,0)+G16 -> 44505 | J16: x | K16: STI | L16: 1550 | M16: 0 | N16: =IF(Q16="x",0,0.04*L16) -> 62 | O16: 2 | P16: =L16+N16+O16 -> 1614 | T16: forfettario | Z16: 2500 | AF16: 44501 | AG16: =AF17-1 -> -1 | AH16: =NETWORKDAYS(AF16,AG16) -> #NUM!
A17: 13 | E17: =IF(#REF!="CASA",CONCATENATE("C:\Users\studi\Google Drive\CONTABILITA'\2020\Fatture\",D17," Trimestre\",B17,".pdf"),CONCATENATE("C:\Users\Sebastiano\Google Drive\CONTABILITA'\2020\Fatture\",D17," Trimestre\",B17,".pdf")) -> #REF! | F17: 44530 | G17: 5 | H17: =EOMONTH(F17,0)+G17 -> 44535 | J17: x | K17: STI | L17: 2500 | M17: 0 | N17: =IF(Q17="x",0,0.04*L17) -> 100 | O17: 2 | P17: =L17+N17+O17 -> 2602 | S17: Totale fatturato annuo | T17: =L28 -> 38022 | Z17: 2500
A18: 14 | E18: =IF(#REF!="CASA",CONCATENATE("C:\Users\studi\Google Drive\CONTABILITA'\2020\Fatture\",D18," Trimestre\",B18,".pdf"),CONCATENATE("C:\Users\Sebastiano\Google Drive\CONTABILITA'\2020\Fatture\",D18," Trimestre\",B18,".pdf")) -> #REF! | F18: 44549 | G18: 5 | H18: =EOMONTH(F18,0)+G18 -> 44566 | J18: x | K18: Mattia Coppino | L18: 1250 | M18: 0 | N18: =IF(Q18="x",0,0.04*L18) -> 50 | O18: 2 | P18: =L18+N18+O18 -> 1302 | S18: volume d'affari compessivo | T18: =T17+SUMIF(J5:J26,"x",(O5:O26)) -> 38044
A19: 15 | E19: =IF(#REF!="CASA",CONCATENATE("C:\Users\studi\Google Drive\CONTABILITA'\2020\Fatture\",D19," Trimestre\",B19,".pdf"),CONCATENATE("C:\Users\Sebastiano\Google Drive\CONTABILITA'\2020\Fatture\",D19," Trimestre\",B19,".pdf")) -> #REF! | F19: 44557 | G19: 5 | H19: =EOMONTH(F19,0)+G19 -> 44566 | J19: x | K19: Andrea Coppino | L19: 3500 | M19: 0 | N19: =IF(Q19="x",0,0.04*L19) -> 140 | O19: 2 | P19: =L19+N19+O19 -> 3642 | S19: Spese deducibili
A20: 16 | E20: =IF(#REF!="CASA",CONCATENATE("C:\Users\studi\Google Drive\CONTABILITA'\2020\Fatture\",D20," Trimestre\",B20,".pdf"),CONCATENATE("C:\Users\Sebastiano\Google Drive\CONTABILITA'\2020\Fatture\",D20," Trimestre\",B20,".pdf")) -> #REF! | S20: Imponibile | T20: =ROUND(T17*0.78,0) -> 29657
A21: 17 | E21: =IF(#REF!="CASA",CONCATENATE("C:\Users\studi\Google Drive\CONTABILITA'\2020\Fatture\",D21," Trimestre\",B21,".pdf"),CONCATENATE("C:\Users\Sebastiano\Google Drive\CONTABILITA'\2020\Fatture\",D21," Trimestre\",B21,".pdf")) -> #REF! | J21: =IF(I21<>"","x","") | S21: Imposta sostitutiva (15% al fisco) | T21: =0.15*T20 -> 4448.55
A22: 18 | E22: =IF(#REF!="CASA",CONCATENATE("C:\Users\studi\Google Drive\CONTABILITA'\2020\Fatture\",D22," Trimestre\",B22,".pdf"),CONCATENATE("C:\Users\Sebastiano\Google Drive\CONTABILITA'\2020\Fatture\",D22," Trimestre\",B22,".pdf")) -> #REF! | J22: =IF(I22<>"","x","")
A23: 19 | E23: =IF(#REF!="CASA",CONCATENATE("C:\Users\studi\Google Drive\CONTABILITA'\2020\Fatture\",D23," Trimestre\",B23,".pdf"),CONCATENATE("C:\Users\Sebastiano\Google Drive\CONTABILITA'\2020\Fatture\",D23," Trimestre\",B23,".pdf")) -> #REF! | J23: =IF(I23<>"","x","") | S23: INARCASSA | V23: Già pagato | W23: Da pagare | Y23: INARCASSA REALE | AB23: IRPEF REALE
A24: 20 | E24: =IF(#REF!="CASA",CONCATENATE("C:\Users\studi\Google Drive\CONTABILITA'\2020\Fatture\",D24," Trimestre\",B24,".pdf"),CONCATENATE("C:\Users\Sebastiano\Google Drive\CONTABILITA'\2020\Fatture\",D24," Trimestre\",B24,".pdf")) -> #REF! | J24: =IF(I24<>"","x","") | S24: Contributo soggettivo | T24: =MAX(780,0.0725*T20)*2 -> 4300.265 | V24: 532.75 | W24: =T24-V24 -> 3767.515 | Z24: =393.25*2+117.5*2+20+27+6+3515.77+755.88 -> 5346.15 | AC24: 4323
A25: 21 | E25: =IF(#REF!="CASA",CONCATENATE("C:\Users\studi\Google Drive\CONTABILITA'\2020\Fatture\",D25," Trimestre\",B25,".pdf"),CONCATENATE("C:\Users\Sebastiano\Google Drive\CONTABILITA'\2020\Fatture\",D25," Trimestre\",B25,".pdf")) -> #REF! | J25: =IF(I25<>"","x","") | S25: Contributo integrativo | T25: =MAX(231.5,N27) -> 990.88 | V25: 541.75 | W25: =T25-V25 -> 449.13
A26: 22 | E26: =IF(#REF!="CASA",CONCATENATE("C:\Users\studi\Google Drive\CONTABILITA'\2020\Fatture\",D26," Trimestre\",B26,".pdf"),CONCATENATE("C:\Users\Sebastiano\Google Drive\CONTABILITA'\2020\Fatture\",D26," Trimestre\",B26,".pdf")) -> #REF! | J26: =IF(I26<>"","x","") | S26: Contributo maternità | T26: 39 | V26: 4269.65 | W26: =T26-V26 -> -4230.65
K27: totale fatturato | L27: =SUBTOTAL(9,L5:L26) -> 38022 | N27: =SUBTOTAL(9,N5:N26) -> 990.88 | O27: TOT | P27: =SUBTOTAL(9,P5:P26) -> 39034.88 | T27: =SUM(T24:T26) -> 5330.145 | V27: =SUM(V24:V26) -> 5344.15 | W27: =SUM(W24:W26) -> -14.005 | AF27: =SUM(AF24:AF26) -> 0 | AG27: =SUM(AG24:AG26) -> 0 | AH27: =SUM(AH24:AH26) -> 0
K28: totale incassato | L28: =SUMIF(J5:J26,"x",L5:L26) -> 38022 | T28: =(P27-T30)/P27 -> 0.25051172 | U28: =1-(L27-T21-T24-T26)/L27 -> 0.23112448
T29: Netti | U29: Tasse senza 4%
S30: totale | T30: =P27-T21-T27 -> 29256.185 | U30: =L27-T30 -> 8765.815
S31: 2020 | T31: =T36*T7 -> 5641.0085 | U31: =X5+X6-T31 -> 1595.9915
S32: 2021 | T32: =T37*U7+T35 -> 22639.343 | U32: =U30-U31-U34-U35 -> 6125.2936 | X32: Pagato | Y32: 44865 | Z32: 44896 | AA32: Totale | AB32: Rimanente
X33: Inarcassa | Y33: =T24+0.5*T25 -> 4795.705
S34: Mattia | T34: =(SUM(P18)-(T21+T27)/(P27)*SUM(P18)) -> 975.83374 | U34: =L18-T34 -> 274.16626 | X34: Imposte | Y34: 5755 | Z34: 2161.5 | AA34: =Z34+Y34 -> 7916.5 | AB34: =AA34-T21 -> 3467.95
Q35: =(T37*U7+T36*T7+T35)/(T7+U7) -> 1663.5501 | R35: Media | S35: Andrea | T35: =(SUM(P19)-(T21+T27)/(P27)*SUM(P19)) -> 2729.6363 | U35: =L19-T35 -> 770.36369
O36: =(T37*U7+T35)/U7 -> 1886.6119 | P36: Media | S36: mensile anno prec | T36: =(SUM(X5:X6)*1.04-(T21+T27)/(P27)*SUM(X5:X6)*1.04)/T7 -> 1128.2017 | U36: =U31/T7 -> 319.19829
S37: mensile anno attuale | T37: =(P27-SUM(X5:X6)*1.04-P18-P19-(T21+T27)/(P27)*(P27-SUM(X5:X6)*1.04-P18-P19))/U7 -> 1659.1422 | U37: =U32/U7 -> 510.44113
S38: Controllo | T38: =T37*U7+T36*T7+T27+T21+T34+T35 -> 39034.88

Sheet 2022 reale
C1: ELENCO FATTURE
C2: Anno 2022 | J2: Anno 2017
B4: Numero | C4: NOTE | E4: Mese | G4: Data emissione | H4: Destinatario | I4: Netto | J4: Iva | K4: Integr. 4% | L4: Bollo | M4: Totale | N4: Estero
B5: 16 | E5: Dicembre | G5: 44561 | H5: STI | I5: 500 | J5: 0 | K5: =IF(N5="x",0,0.04*I5) -> 0 | L5: 2 | M5: =I5+K5+L5 -> 502 | N5: x
B6: 17 | E6: Dicembre | G6: 44561 | H6: STI | I6: 2000 | J6: 0 | K6: =IF(N6="x",0,0.04*I6) -> 80 | L6: 2 | M6: =I6+K6+L6 -> 2082
B7: 1 | E7: Gennaio | F7: =IF(#REF!="CASA",CONCATENATE("C:\Users\studi\Google Drive\CONTABILITA'\",D7,"\",E7," Trimestre\Fatture\",C7,".pdf"),CONCATENATE("C:\Users\Sebastiano\Google Drive\CONTABILITA'\",D7,"\",E7," Trimestre\Fatture\",C7,".pdf")) -> #REF! | G7: 44592 | H7: STI | I7: 2800 | J7: 0 | K7: =IF(N7="x",0,0.04*I7) -> 112 | L7: 2 | M7: =I7+K7+L7 -> 2914
B8: 2 | E8: Febbraio | F8: =IF(#REF!="CASA",CONCATENATE("C:\Users\studi\Google Drive\CONTABILITA'\2019\",E8," Trimestre\Fatture\",C8,".pdf"),CONCATENATE("C:\Users\Sebastiano\Google Drive\CONTABILITA'\2019\",E8," Trimestre\Fatture\",C8,".pdf")) -> #REF! | G8: 44620 | H8: STI | I8: 2800 | J8: 0 | K8: =IF(N8="x",0,0.04*I8) -> 112 | L8: 2 | M8: =I8+K8+L8 -> 2914
B9: 3 | E9: Marzo | F9: =IF(#REF!="CASA",CONCATENATE("C:\Users\studi\Google Drive\CONTABILITA'\2019\",E9," Trimestre\Fatture\",C9,".pdf"),CONCATENATE("C:\Users\Sebastiano\Google Drive\CONTABILITA'\2019\",E9," Trimestre\Fatture\",C9,".pdf")) -> #REF! | G9: 44651 | H9: STI | I9: 2800 | J9: 0 | K9: =IF(N9="x",0,0.04*I9) -> 112 | L9: 2 | M9: =I9+K9+L9 -> 2914
B10: 4 | E10: Aprile | F10: =IF(#REF!="CASA",CONCATENATE("C:\Users\studi\Google Drive\CONTABILITA'\2020\",E10," Trimestre\Fatture\",C10,".pdf"),CONCATENATE("C:\Users\Sebastiano\Google Drive\CONTABILITA'\2020\",E10," Trimestre\Fatture\",C10,".pdf")) -> #REF! | G10: 44681 | H10: STI | I10: 2800 | J10: 0 | K10: =IF(N10="x",0,0.04*I10) -> 112 | L10: 2 | M10: =I10+K10+L10 -> 2914
B11: 5 | E11: Maggio | F11: =IF(#REF!="CASA",CONCATENATE("C:\Users\studi\Google Drive\CONTABILITA'\2020\Fatture\",E11," Trimestre\",C11,".pdf"),CONCATENATE("C:\Users\Sebastiano\Google Drive\CONTABILITA'\2020\Fatture\",E11," Trimestre\",C11,".pdf")) -> #REF! | G11: 44712 | H11: STI | I11: 2800 | J11: 0 | K11: =IF(N11="x",0,0.04*I11) -> 112 | L11: 2 | M11: =I11+K11+L11 -> 2914
B12: 6 | E12: Giugno | F12: =IF(#REF!="CASA",CONCATENATE("C:\Users\studi\Google Drive\CONTABILITA'\2020\Fatture\",E12," Trimestre\",C12,".pdf"),CONCATENATE("C:\Users\Sebastiano\Google Drive\CONTABILITA'\2020\Fatture\",E12," Trimestre\",C12,".pdf")) -> #REF! | G12: 44712 | H12: STI | I12: 2800 | J12: 0 | K12: =IF(N12="x",0,0.04*I12) -> 112 | L12: 2 | M12: =I12+K12+L12 -> 2914
B13: 7 | E13: Giugno | G13: 44742 | H13: Tosolini | I13: 400 | J13: 0 | K13: =IF(N13="x",0,0.04*I13) -> 16 | L13: 2 | M13: =I13+K13+L13 -> 418
B14: 8 | E14: Luglio | F14: =IF(#REF!="CASA",CONCATENATE("C:\Users\studi\Google Drive\CONTABILITA'\2020\Fatture\",E14," Trimestre\",C14,".pdf"),CONCATENATE("C:\Users\Sebastiano\Google Drive\CONTABILITA'\2020\Fatture\",E14," Trimestre\",C14,".pdf")) -> #REF! | G14: 44798 | H14: STI | I14: 2500 | J14: 0 | K14: =IF(N14="x",0,0.04*I14) -> 100 | L14: 2 | M14: =I14+K14+L14 -> 2602
B15: 9 | C15: SBAGLIATA | E15: Agosto | F15: =IF(#REF!="CASA",CONCATENATE("C:\Users\studi\Google Drive\CONTABILITA'\2020\Fatture\",E15," Trimestre\",C15,".pdf"),CONCATENATE("C:\Users\Sebastiano\Google Drive\CONTABILITA'\2020\Fatture\",E15," Trimestre\",C15,".pdf")) -> #REF! | G15: 44831 | H15: STI | I15: 1698 | J15: 0 | K15: =IF(N15="x",0,0.04*I15) -> 67.92 | L15: 2 | M15: =I15+K15+L15 -> 1767.92
B16: 1 | C16: NOTA DI CREDITO | G16: 44831 | H16: STI | I16: -1698 | J16: 0 | K16: =IF(N16="x",0,0.04*I16) -> -67.92 | L16: -2 | M16: =I16+K16+L16 -> -1767.92
B17: 10 | E17: Agosto | F17: =IF(#REF!="CASA",CONCATENATE("C:\Users\studi\Google Drive\CONTABILITA'\2020\Fatture\",E17," Trimestre\",C17,".pdf"),CONCATENATE("C:\Users\Sebastiano\Google Drive\CONTABILITA'\2020\Fatture\",E17," Trimestre\",C17,".pdf")) -> #REF! | G17: 44833 | H17: STI | I17: 1632.69 | J17: 0 | K17: =IF(N17="x",0,0.04*I17) -> 65.3076 | L17: 2 | M17: =I17+K17+L17 -> 1699.9976 | Q17: Coefficiente ATECO | R17: 0.78
B18: 11 | C18: Data emissione sbagliata, già pagato F24 | E18: Settembre | F18: =IF(#REF!="CASA",CONCATENATE("C:\Users\studi\Google Drive\CONTABILITA'\2020\Fatture\",E18," Trimestre\",C18,".pdf"),CONCATENATE("C:\Users\Sebastiano\Google Drive\CONTABILITA'\2020\Fatture\",E18," Trimestre\",C18,".pdf")) -> #REF! | G18: 44833 | H18: STI | I18: 2500 | J18: 0 | K18: =IF(N18="x",0,0.04*I18) -> 100 | L18: 2 | M18: =I18+K18+L18 -> 2602
B19: 12 | E19: Ottobre | F19: =IF(#REF!="CASA",CONCATENATE("C:\Users\studi\Google Drive\CONTABILITA'\2020\Fatture\",E19," Trimestre\",C19,".pdf"),CONCATENATE("C:\Users\Sebastiano\Google Drive\CONTABILITA'\2020\Fatture\",E19," Trimestre\",C19,".pdf")) -> #REF! | G19: 44895 | H19: STI | I19: 2500 | J19: 0 | K19: =IF(N19="x",0,0.04*I19) -> 100 | L19: 2 | M19: =I19+K19+L19 -> 2602 | Q19: forfettario
B20: 13 | E20: Saldo agosto | F20: =IF(#REF!="CASA",CONCATENATE("C:\Users\studi\Google Drive\CONTABILITA'\2020\Fatture\",E20," Trimestre\",C20,".pdf"),CONCATENATE("C:\Users\Sebastiano\Google Drive\CONTABILITA'\2020\Fatture\",E20," Trimestre\",C20,".pdf")) -> #REF! | G20: 44900 | H20: STI | I20: 865.38 | J20: 0 | K20: =IF(N20="x",0,0.04*I20) -> 34.6152 | L20: 2 | M20: =I20+K20+L20 -> 901.9952 | P20: Totale fatturato annuo | Q20: =I31 -> 32198.07
B21: 14 | E21: Novembre | F21: =IF(#REF!="CASA",CONCATENATE("C:\Users\studi\Google Drive\CONTABILITA'\2020\Fatture\",E21," Trimestre\",C21,".pdf"),CONCATENATE("C:\Users\Sebastiano\Google Drive\CONTABILITA'\2020\Fatture\",E21," Trimestre\",C21,".pdf")) -> #REF! | G21: 44922 | H21: STI | I21: 2500 | J21: 0 | K21: =IF(N21="x",0,0.04*I21) -> 100 | L21: 2 | M21: =I21+K21+L21 -> 2602 | P21: volume d'affari compessivo | Q21: =Q20+SUM(L5:L29) -> 32228.07
P22: Spese deducibili | V22: INARCASSA REALE | Y22: IRPEF REALE
P23: Imponibile | Q23: =0.78*Q20 -> 25114.495 | S23: Già pagato | T23: Da pagare | W23: 3137.55 | Z23: 3119
P24: Imposta sostitutiva (15% al fisco) | Q24: =0.15*(Q23-4346) -> 3115.2742 | S24: =2161.5*2 -> 4323 | T24: =Q24-S24 -> -1207.7258
P26: INARCASSA | S26: Già pagato | T26: Da pagare
P27: Contributo soggettivo | Q27: =MAX(780,0.0725*Q23) -> 1820.8009 | S27: 539 | T27: =Q27-S27 -> 1281.8009
P28: Contributo integrativo | Q28: =MAX(231.5,K30) -> 1267.9228 | S28: 530 | T28: =Q28-S28 -> 737.9228
P29: Contributo maternità | Q29: 44 | S29: 2066.55 | T29: =Q29-S29 -> -2022.55
H30: totale fatturato | I30: =SUBTOTAL(9,I5:I29) -> 32198.07 | K30: =SUBTOTAL(9,K5:K29) -> 1267.9228 | L30: TOT | M30: =SUBTOTAL(9,M5:M29) -> 33495.993 | Q30: =SUM(Q27:Q29) -> 3132.7237 | S30: =SUM(S27:S29) -> 3135.55 | T30: =SUM(T27:T29) -> -2.8263415
H31: totale incassato | I31: =SUM(I5:I29) -> 32198.07
Q32: =(M30-Q33)/M30 -> 0.18652971 | R32: =1-(I30-Q24-Q27-Q29)/I30 -> 0.15466999
G33: A1 | H33: =H34*0.78*0+25138 -> 25138 | I33: preso dal commericalista LM22 colonna 5 | P33: Netto totale | Q33: =M30-Q24-Q30 -> 27247.995
G34: B1 | H34: =(SUM(I5:I29)+SUM(L5:L29))*0+32228 -> 32228 | I34: preso dal commericalista LM22 colonna 3
G35: B2.1 | H35: =SUMIFS(I5:I29,N5:N29,I35)+SUMIFS(L5:L29,N5:N29,I35) -> 31726.07 | I35: ="" | P35: Netto mensile anno attuale | Q35: =Q33/12 -> 2270.6662 | S35: Rimanente | T35: =T24+T30 -> -1210.5522
G36: B5.1 | H36: =SUMIFS(I5:I29,N5:N29,I36)+SUMIFS(L5:L29,N5:N29,I36) -> 502 | I36: x | P36: Netto mensile 13 mensilità | Q36: =Q35/13*12 -> 2095.9996
G37: B7.1 | H37: =H35 -> 31726.07
G38: E1 | H38: =K30 -> 1267.9228

Sheet 2023 reale
C1: ELENCO FATTURE
C2: Anno 2023 | J2: Anno 2017
B4: Numero | C4: NOTE | E4: Mese | G4: Data emissione | H4: Destinatario | I4: Netto | J4: Iva | K4: Integr. 4% | L4: Bollo | M4: Totale | N4: Estero
B5: 1 | D5: 44952 | E5: Dicembre | H5: STI | I5: 2500 | J5: 0 | K5: =IF(N5="x",0,0.04*I5) -> 100 | L5: 2 | M5: =I5+K5+L5 -> 2602 | U5: =6595-2920 -> 3675
B6: 2 | D6: 44981 | E6: Gennaio | F6: =IF(#REF!="CASA",CONCATENATE("C:\Users\studi\Google Drive\CONTABILITA'\",D6,"\",E6," Trimestre\Fatture\",C6,".pdf"),CONCATENATE("C:\Users\Sebastiano\Google Drive\CONTABILITA'\",D6,"\",E6," Trimestre\Fatture\",C6,".pdf")) -> #REF! | H6: STI | I6: 2500 | J6: 0 | K6: =IF(N6="x",0,0.04*I6) -> 100 | L6: 2 | M6: =I6+K6+L6 -> 2602
B7: 3 | D7: 44989 | E7: Febbraio | F7: =IF(#REF!="CASA",CONCATENATE("C:\Users\studi\Google Drive\CONTABILITA'\2019\",E7," Trimestre\Fatture\",C7,".pdf"),CONCATENATE("C:\Users\Sebastiano\Google Drive\CONTABILITA'\2019\",E7," Trimestre\Fatture\",C7,".pdf")) -> #REF! | H7: Pellizzari | I7: 900 | J7: 0 | K7: =IF(N7="x",0,0.04*I7) -> 36 | L7: 2 | M7: =I7+K7+L7 -> 938
B8: 4 | D8: 45009 | E8: Febbraio | F8: =IF(#REF!="CASA",CONCATENATE("C:\Users\studi\Google Drive\CONTABILITA'\2019\",E8," Trimestre\Fatture\",C8,".pdf"),CONCATENATE("C:\Users\Sebastiano\Google Drive\CONTABILITA'\2019\",E8," Trimestre\Fatture\",C8,".pdf")) -> #REF! | H8: STI | I8: 2500 | J8: 0 | K8: =IF(N8="x",0,0.04*I8) -> 100 | L8: 2 | M8: =I8+K8+L8 -> 2602
B9: 5 | D9: 45022 | E9: Marzo | F9: =IF(#REF!="CASA",CONCATENATE("C:\Users\studi\Google Drive\CONTABILITA'\2020\",E9," Trimestre\Fatture\",C9,".pdf"),CONCATENATE("C:\Users\Sebastiano\Google Drive\CONTABILITA'\2020\",E9," Trimestre\Fatture\",C9,".pdf")) -> #REF! | H9: STI | I9: 2500 | J9: 0 | K9: =IF(N9="x",0,0.04*(I9+L9)) -> 100.08 | L9: 2 | M9: =I9+K9+L9 -> 2602.08
B10: 6 | D10: 45046 | E10: Aprile | F10: =IF(#REF!="CASA",CONCATENATE("C:\Users\studi\Google Drive\CONTABILITA'\2020\Fatture\",E10," Trimestre\",C10,".pdf"),CONCATENATE("C:\Users\Sebastiano\Google Drive\CONTABILITA'\2020\Fatture\",E10," Trimestre\",C10,".pdf")) -> #REF! | H10: STI | I10: 2800 | J10: 0 | K10: =IF(N10="x",0,0.04*(I10+L10)) -> 112.08 | L10: 2 | M10: =I10+K10+L10 -> 2914.08
B11: 7 | D11: 45077 | E11: Maggio | F11: =IF(#REF!="CASA",CONCATENATE("C:\Users\studi\Google Drive\CONTABILITA'\2020\Fatture\",E11," Trimestre\",C11,".pdf"),CONCATENATE("C:\Users\Sebastiano\Google Drive\CONTABILITA'\2020\Fatture\",E11," Trimestre\",C11,".pdf")) -> #REF! | H11: STI | I11: 2650 | J11: 0 | K11: 0 | L11: 2 | M11: =I11+K11+L11 -> 2652 | N11: ESTERO
B12: 8 | D12: 45169 | E12: Giugno | F12: =IF(#REF!="CASA",CONCATENATE("C:\Users\studi\Google Drive\CONTABILITA'\2020\Fatture\",E12," Trimestre\",C12,".pdf"),CONCATENATE("C:\Users\Sebastiano\Google Drive\CONTABILITA'\2020\Fatture\",E12," Trimestre\",C12,".pdf")) -> #REF! | H12: STI | I12: 2650 | J12: 0 | K12: 0 | L12: 2 | M12: =I12+K12+L12 -> 2652 | N12: ESTERO
B13: 9 | D13: 45169 | E13: Luglio | F13: =IF(#REF!="CASA",CONCATENATE("C:\Users\studi\Google Drive\CONTABILITA'\2020\Fatture\",E13," Trimestre\",C13,".pdf"),CONCATENATE("C:\Users\Sebastiano\Google Drive\CONTABILITA'\2020\Fatture\",E13," Trimestre\",C13,".pdf")) -> #REF! | H13: STI | I13: =2650+(31-16+1)*25+469.95 -> 3519.95 | J13: 0 | K13: 0 | L13: 2 | M13: =I13+K13+L13 -> 3521.95 | N13: ESTERO | O13: =M13-M12 -> 869.95 | Q13: Coefficiente ATECO | R13: 0.78
B14: 10 | D14: 45169 | E14: Agosto | F14: =IF(#REF!="CASA",CONCATENATE("C:\Users\studi\Google Drive\CONTABILITA'\2020\Fatture\",E14," Trimestre\",C14,".pdf"),CONCATENATE("C:\Users\Sebastiano\Google Drive\CONTABILITA'\2020\Fatture\",E14," Trimestre\",C14,".pdf")) -> #REF! | H14: STI | I14: =2650+(5-1+1)*25+131.06 -> 2906.06 | J14: 0 | K14: 0 | L14: 2 | M14: =I14+K14+L14 -> 2908.06 | N14: ESTERO
B15: 11 | D15: 45199 | E15: Settembre | F15: =IF(#REF!="CASA",CONCATENATE("C:\Users\studi\Google Drive\CONTABILITA'\2020\Fatture\",E15," Trimestre\",C15,".pdf"),CONCATENATE("C:\Users\Sebastiano\Google Drive\CONTABILITA'\2020\Fatture\",E15," Trimestre\",C15,".pdf")) -> #REF! | H15: STI | I15: 2900 | J15: 0 | K15: 0 | L15: 2 | M15: =I15+K15+L15 -> 2902 | N15: ESTERO | Q15: forfettario
B16: 12 | D16: 45230 | E16: Ottobre | F16: =IF(#REF!="CASA",CONCATENATE("C:\Users\studi\Google Drive\CONTABILITA'\2020\Fatture\",E16," Trimestre\",C16,".pdf"),CONCATENATE("C:\Users\Sebastiano\Google Drive\CONTABILITA'\2020\Fatture\",E16," Trimestre\",C16,".pdf")) -> #REF! | H16: STI | I16: 2900 | J16: 0 | K16: 0 | L16: 2 | M16: =I16+K16+L16 -> 2902 | N16: ESTERO | P16: Totale fatturato annuo | Q16: =I27 -> 34126.01
B17: 13 | D17: 45260 | E17: Novembre | F17: =IF(#REF!="CASA",CONCATENATE("C:\Users\studi\Google Drive\CONTABILITA'\2020\Fatture\",E17," Trimestre\",C17,".pdf"),CONCATENATE("C:\Users\Sebastiano\Google Drive\CONTABILITA'\2020\Fatture\",E17," Trimestre\",C17,".pdf")) -> #REF! | H17: STI | I17: 2900 | J17: 0 | K17: 0 | L17: 2 | M17: =I17+K17+L17 -> 2902 | N17: ESTERO | P17: volume d'affari compessivo | Q17: =Q16+SUM(L5:L25) -> 34152.01
P18: Spese deducibili | R18: LIMITE
P19: Imponibile | Q19: =0.78*Q17 -> 26638.568 | R19: 31704 | S19: Già pagato | T19: Da pagare
P20: Imposta sostitutiva (15% al fisco) | Q20: =0.15*(Q19-Q26) -> 3614.8667 | R20: Extra | S20: =1559.5*2+589 -> 3708 | T20: =(Q20-S20)*0 -> 0
R21: =(R19-Q19)/0.78 -> 6494.1438
P22: INARCASSA | R22: Ridotto | S22: Già pagato | T22: Da pagare
P23: Contributo soggettivo | Q23: =MAX(780,0.0725*Q19)*IF(R23="Sì",1,2) -> 1931.2962 | R23: =IF(R21>0,"Sì","No") -> Sì | S23: 558.75 | T23: =Q23-S23 -> 1372.5462
P24: Contributo integrativo | Q24: =MAX(231.5,K26) -> 548.16 | S24: 574.75 | T24: =Q24-S24 -> -26.59
P25: Contributo maternità | Q25: 60 | S25: 1406.31 | T25: =Q25-S25 -> -1346.31
H26: totale fatturato | I26: =SUBTOTAL(9,I5:I25) -> 34126.01 | K26: =SUBTOTAL(9,K5:K25) -> 548.16 | L26: TOT | M26: =SUBTOTAL(9,M5:M25) -> 34700.17 | Q26: =SUM(Q23:Q25) -> 2539.4562 | S26: =SUM(S23:S25) -> 2539.81 | T26: =SUM(T23:T25)*0 -> 0
H27: totale incassato | I27: =SUM(I5:I25) -> 34126.01
Q28: =(M26-Q29)/M26 -> 0.17735714 | R28: =1-(I26-Q20-Q23-Q25)/I26 -> 0.1642783
P29: Netto totale | Q29: =M26-Q20-Q26 -> 28545.847
P31: Netto mensile anno attuale | Q31: =Q29/12 -> 2378.8206 | S31: Rimanente | T31: =T26+T20 -> 0
P32: Netto mensile 13 mensilità | Q32: =Q31/13*12 -> 2195.8344
G33: A1 | H33: =H34*0.78*0+26639 -> 26639 | I33: preso dal commericalista LM22 colonna 5
G34: B1 | H34: =(SUM(I5:I29)+SUM(L5:L29))*0+34152 -> 34152 | I34: preso dal commericalista LM22 colonna 3
G35: B2.1 | H35: =SUMIFS(I5:I25,N5:N25,I35)+SUMIFS(L5:L25,N5:N25,I35) -> 13712 | I35: =""
G36: B5.1 | H36: =SUMIFS(I5:I25,N5:N25,I36)+SUMIFS(L5:L25,N5:N25,I36) -> 20440.01 | I36: ESTERO | J36: CHECK!
G37: B7.1 | H37: =H35 -> 13712 | J37: =H34-H35-H36 -> -0.01 | K37: <1€
G38: E1 | H38: =K26 -> 548.16

Sheet Linea
B1: ELENCO FATTURE
B2: Anno 2021 | M2: Anno 2017 | S2: GIORNI FESTIVI | T2: 6
S3: Ferie | T3: 20 | Z3: x
B4: Nr | C4: Anno | D4: Trimestre | F4: Data emissione | G4: Pagamento (gg) | H4: Data Scadenza | I4: Data pagamento | J4: Incassato | K4: Destinatario | L4: Netto | M4: Iva | N4: Integr. 4% | O4: Bollo | P4: Totale | Y4: Ferie | Z4: Extra Alessandro | AA4: Fattura reale | AB4: Fattura stimata
A5: 1 | E5: =IF(#REF!="CASA",CONCATENATE("C:\Users\studi\Google Drive\CONTABILITA'\",C5,"\",D5," Trimestre\Fatture\",B5,".pdf"),CONCATENATE("C:\Users\Sebastiano\Google Drive\CONTABILITA'\",C5,"\",D5," Trimestre\Fatture\",B5,".pdf")) -> #REF! | F5: 44227 | G5: 5 | H5: =EOMONTH(F5,0)+G5 -> 44232 | J5: x | K5: Linea | L5: =IF($T$7>=A5,IF(AA5="",AB5,AA5),0)+Z5 -> 2260 | M5: 0 | N5: =0.04*L5 -> 90.4 | O5: 0 | P5: =L5+N5+O5 -> 2350.4 | V5: 44197 | W5: =V6-1 -> 44227 | X5: =NETWORKDAYS(V5,W5) -> 21 | Y5: =($T$3+$T$2)/$T$7 -> 2.1666667 | Z5: =IF(Z3="",3737,0) -> 0 | AA5: =IF(Z3="",1850,"") | AB5: =IF(AC5="x",(X5-Y5)*120,(X5-Y5)*$S$9*$S$8) -> 2260 | AC5: x
A6: 2 | E6: =IF(#REF!="CASA",CONCATENATE("C:\Users\studi\Google Drive\CONTABILITA'\2019\",D6," Trimestre\Fatture\",B6,".pdf"),CONCATENATE("C:\Users\Sebastiano\Google Drive\CONTABILITA'\2019\",D6," Trimestre\Fatture\",B6,".pdf")) -> #REF! | F6: 44255 | G6: 5 | H6: =EOMONTH(F6,0)+G6 -> 44260 | J6: x | K6: Linea | L6: =IF($T$7>=A6,IF(AA6="",AB6,AA6),0)+Z6 -> 2140 | M6: 0 | N6: =0.04*L6 -> 85.6 | O6: 0 | P6: =L6+N6+O6 -> 2225.6 | S6: Precedenti | T6: Attuali | V6: 44228 | W6: =V7-1 -> 44255 | X6: =NETWORKDAYS(V6,W6) -> 20 | Y6: =($T$3+$T$2)/$T$7 -> 2.1666667 | Z6: =IF(Z3="",3500,0) -> 0 | AA6: =IF(Z3="",1760,"") | AB6: =IF(AC6="x",(X6-Y6)*120,(X6-Y6)*$S$9*$S$8) -> 2140 | AC6: x
A7: 3 | E7: =IF(#REF!="CASA",CONCATENATE("C:\Users\studi\Google Drive\CONTABILITA'\2019\",D7," Trimestre\Fatture\",B7,".pdf"),CONCATENATE("C:\Users\Sebastiano\Google Drive\CONTABILITA'\2019\",D7," Trimestre\Fatture\",B7,".pdf")) -> #REF! | F7: 44286 | G7: 5 | H7: =EOMONTH(F7,0)+G7 -> 44291 | J7: x | K7: Linea | L7: =IF($T$7>=A7,IF(AA7="",AB7,AA7),0)+Z7 -> 2500 | M7: 0 | N7: =0.04*L7 -> 100 | O7: 0 | P7: =L7+N7+O7 -> 2600 | R7: Mesi | S7: 0 | T7: 12 | V7: 44256 | W7: =V8-1 -> 44286 | X7: =NETWORKDAYS(V7,W7) -> 23 | Y7: =($T$3+$T$2)/$T$7 -> 2.1666667 | AB7: =IF(AC7="x",(X7-Y7)*120,(X7-Y7)*$S$9*$S$8) -> 2500 | AC7: x
A8: 4 | E8: =IF(#REF!="CASA",CONCATENATE("C:\Users\studi\Google Drive\CONTABILITA'\2020\",D8," Trimestre\Fatture\",B8,".pdf"),CONCATENATE("C:\Users\Sebastiano\Google Drive\CONTABILITA'\2020\",D8," Trimestre\Fatture\",B8,".pdf")) -> #REF! | F8: 44316 | G8: 5 | H8: =EOMONTH(F8,0)+G8 -> 44321 | J8: x | K8: Linea | L8: =IF($T$7>=A8,IF(AA8="",AB8,AA8),0)+Z8 -> 2380 | M8: 0 | N8: =0.04*L8 -> 95.2 | O8: 0 | P8: =L8+N8+O8 -> 2475.2 | S8: 10 | V8: 44287 | W8: =V9-1 -> 44316 | X8: =NETWORKDAYS(V8,W8) -> 22 | Y8: =($T$3+$T$2)/$T$7 -> 2.1666667 | AB8: =IF(AC8="x",(X8-Y8)*120,(X8-Y8)*$S$9*$S$8) -> 2380 | AC8: x
A9: 5 | E9: =IF(#REF!="CASA",CONCATENATE("C:\Users\studi\Google Drive\CONTABILITA'\2020\Fatture\",D9," Trimestre\",B9,".pdf"),CONCATENATE("C:\Users\Sebastiano\Google Drive\CONTABILITA'\2020\Fatture\",D9," Trimestre\",B9,".pdf")) -> #REF! | F9: 44347 | G9: 5 | H9: =EOMONTH(F9,0)+G9 -> 44352 | J9: x | K9: Linea | L9: =IF($T$7>=A9,IF(AA9="",AB9,AA9),0)+Z9 -> 2260 | M9: 0 | N9: =0.04*L9 -> 90.4 | O9: 0 | P9: =L9+N9+O9 -> 2350.4 | R9: Ore | S9: 9 | V9: 44317 | W9: =V10-1 -> 44347 | X9: =NETWORKDAYS(V9,W9) -> 21 | Y9: =($T$3+$T$2)/$T$7 -> 2.1666667 | AB9: =IF(AC9="x",(X9-Y9)*120,(X9-Y9)*$S$9*$S$8) -> 2260 | AC9: x
A10: 6 | E10: =IF(#REF!="CASA",CONCATENATE("C:\Users\studi\Google Drive\CONTABILITA'\2020\Fatture\",D10," Trimestre\",B10,".pdf"),CONCATENATE("C:\Users\Sebastiano\Google Drive\CONTABILITA'\2020\Fatture\",D10," Trimestre\",B10,".pdf")) -> #REF! | F10: 44377 | G10: 5 | H10: =EOMONTH(F10,0)+G10 -> 44382 | J10: x | K10: Linea | L10: =IF($T$7>=A10,IF(AA10="",AB10,AA10),0)+Z10 -> 2380 | M10: 0 | N10: =0.04*L10 -> 95.2 | O10: 0 | P10: =L10+N10+O10 -> 2475.2 | R10: Giorni | S10: 21.5 | T10: =S10*S9 -> 193.5 | V10: 44348 | W10: =V11-1 -> 44377 | X10: =NETWORKDAYS(V10,W10) -> 22 | Y10: =($T$3+$T$2)/$T$7 -> 2.1666667 | AB10: =IF(AC10="x",(X10-Y10)*120,(X10-Y10)*$S$9*$S$8) -> 2380 | AC10: x
A11: 7 | E11: =IF(#REF!="CASA",CONCATENATE("C:\Users\studi\Google Drive\CONTABILITA'\2020\Fatture\",D11," Trimestre\",B11,".pdf"),CONCATENATE("C:\Users\Sebastiano\Google Drive\CONTABILITA'\2020\Fatture\",D11," Trimestre\",B11,".pdf")) -> #REF! | F11: 44408 | G11: 5 | H11: =EOMONTH(F11,0)+G11 -> 44413 | J11: x | K11: Linea | L11: =IF($T$7>=A11,IF(AA11="",AB11,AA11),0)+Z11 -> 2380 | M11: 0 | N11: =0.04*L11 -> 95.2 | O11: 0 | P11: =L11+N11+O11 -> 2475.2 | R11: Mensile | S11: =+S10*S9*S8 -> 1935 | V11: 44378 | W11: =V12-1 -> 44408 | X11: =NETWORKDAYS(V11,W11) -> 22 | Y11: =($T$3+$T$2)/$T$7 -> 2.1666667 | AB11: =IF(AC11="x",(X11-Y11)*120,(X11-Y11)*$S$9*$S$8) -> 2380 | AC11: x
A12: 8 | E12: =IF(#REF!="CASA",CONCATENATE("C:\Users\studi\Google Drive\CONTABILITA'\2020\Fatture\",D12," Trimestre\",B12,".pdf"),CONCATENATE("C:\Users\Sebastiano\Google Drive\CONTABILITA'\2020\Fatture\",D12," Trimestre\",B12,".pdf")) -> #REF! | F12: 44439 | G12: 5 | H12: =EOMONTH(F12,0)+G12 -> 44444 | J12: x | K12: Linea | L12: =IF($T$7>=A12,IF(AA12="",AB12,AA12),0)+Z12 -> 2380 | M12: 0 | N12: =0.04*L12 -> 95.2 | O12: 0 | P12: =L12+N12+O12 -> 2475.2 | V12: 44409 | W12: =V13-1 -> 44439 | X12: =NETWORKDAYS(V12,W12) -> 22 | Y12: =($T$3+$T$2)/$T$7 -> 2.1666667 | AB12: =IF(AC12="x",(X12-Y12)*120,(X12-Y12)*$S$9*$S$8) -> 2380 | AC12: x
A13: 9 | E13: =IF(#REF!="CASA",CONCATENATE("C:\Users\studi\Google Drive\CONTABILITA'\2020\Fatture\",D13," Trimestre\",B13,".pdf"),CONCATENATE("C:\Users\Sebastiano\Google Drive\CONTABILITA'\2020\Fatture\",D13," Trimestre\",B13,".pdf")) -> #REF! | F13: 44469 | G13: 5 | H13: =EOMONTH(F13,0)+G13 -> 44474 | J13: x | K13: Linea | L13: =IF($T$7>=A13,IF(AA13="",AB13,AA13),0)+Z13 -> 2380 | M13: 0 | N13: =0.04*L13 -> 95.2 | O13: 0 | P13: =L13+N13+O13 -> 2475.2 | S13: Coefficiente ATECO | T13: 0.78 | V13: 44440 | W13: =V14-1 -> 44469 | X13: =NETWORKDAYS(V13,W13) -> 22 | Y13: =($T$3+$T$2)/$T$7 -> 2.1666667 | AB13: =IF(AC13="x",(X13-Y13)*120,(X13-Y13)*$S$9*$S$8) -> 2380 | AC13: x
A14: 10 | E14: =IF(#REF!="CASA",CONCATENATE("C:\Users\studi\Google Drive\CONTABILITA'\2020\Fatture\",D14," Trimestre\",B14,".pdf"),CONCATENATE("C:\Users\Sebastiano\Google Drive\CONTABILITA'\2020\Fatture\",D14," Trimestre\",B14,".pdf")) -> #REF! | F14: 44500 | G14: 5 | H14: =EOMONTH(F14,0)+G14 -> 44505 | J14: x | K14: Linea | L14: =IF($T$7>=A14,IF(AA14="",AB14,AA14),0)+Z14 -> 2260 | M14: 0 | N14: =0.04*L14 -> 90.4 | O14: 0 | P14: =L14+N14+O14 -> 2350.4 | V14: 44470 | W14: =V15-1 -> 44500 | X14: =NETWORKDAYS(V14,W14) -> 21 | Y14: =($T$3+$T$2)/$T$7 -> 2.1666667 | AB14: =IF(AC14="x",(X14-Y14)*120,(X14-Y14)*$S$9*$S$8) -> 2260 | AC14: x
A15: 11 | E15: =IF(#REF!="CASA",CONCATENATE("C:\Users\studi\Google Drive\CONTABILITA'\2020\Fatture\",D15," Trimestre\",B15,".pdf"),CONCATENATE("C:\Users\Sebastiano\Google Drive\CONTABILITA'\2020\Fatture\",D15," Trimestre\",B15,".pdf")) -> #REF! | F15: 44530 | G15: 5 | H15: =EOMONTH(F15,0)+G15 -> 44535 | J15: x | K15: Linea | L15: =IF($T$7>=A15,IF(AA15="",AB15,AA15),0)+Z15 -> 2380 | M15: 0 | N15: =0.04*L15 -> 95.2 | O15: 0 | P15: =L15+N15+O15 -> 2475.2 | S15: forfettario | V15: 44501 | W15: =V16-1 -> 44530 | X15: =NETWORKDAYS(V15,W15) -> 22 | Y15: =($T$3+$T$2)/$T$7 -> 2.1666667 | AB15: =IF(AC15="x",(X15-Y15)*120,(X15-Y15)*$S$9*$S$8) -> 2380 | AC15: x
A16: 12 | E16: =IF(#REF!="CASA",CONCATENATE("C:\Users\studi\Google Drive\CONTABILITA'\2020\Fatture\",D16," Trimestre\",B16,".pdf"),CONCATENATE("C:\Users\Sebastiano\Google Drive\CONTABILITA'\2020\Fatture\",D16," Trimestre\",B16,".pdf")) -> #REF! | F16: 44561 | G16: 5 | H16: =EOMONTH(F16,0)+G16 -> 44566 | J16: x | K16: Linea | L16: =IF($T$7>=A16,IF(AA16="",AB16,AA16),0)+Z16 -> 2500 | M16: 0 | N16: =0.04*L16 -> 100 | O16: 0 | P16: =L16+N16+O16 -> 2600 | R16: Totale fatturato annuo | S16: =L27 -> 28200 | V16: 44531 | W16: =V17-1 -> 44561 | X16: =NETWORKDAYS(V16,W16) -> 23 | Y16: =($T$3+$T$2)/$T$7 -> 2.1666667 | AB16: =IF(AC16="x",(X16-Y16)*120,(X16-Y16)*$S$9*$S$8) -> 2500 | AC16: x
A17: 13 | E17: =IF(#REF!="CASA",CONCATENATE("C:\Users\studi\Google Drive\CONTABILITA'\2020\Fatture\",D17," Trimestre\",B17,".pdf"),CONCATENATE("C:\Users\Sebastiano\Google Drive\CONTABILITA'\2020\Fatture\",D17," Trimestre\",B17,".pdf")) -> #REF! | R17: volume d'affari compessivo | S17: =S16+SUMIF(J5:J25,"x",(O5:O25)) -> 28200 | V17: 44562 | AB17: =SUM(AB5:AB16)/261/8 -> 13.505747
A18: 14 | E18: =IF(#REF!="CASA",CONCATENATE("C:\Users\studi\Google Drive\CONTABILITA'\2020\Fatture\",D18," Trimestre\",B18,".pdf"),CONCATENATE("C:\Users\Sebastiano\Google Drive\CONTABILITA'\2020\Fatture\",D18," Trimestre\",B18,".pdf")) -> #REF! | R18: Spese deducibili
A19: 15 | E19: =IF(#REF!="CASA",CONCATENATE("C:\Users\studi\Google Drive\CONTABILITA'\2020\Fatture\",D19," Trimestre\",B19,".pdf"),CONCATENATE("C:\Users\Sebastiano\Google Drive\CONTABILITA'\2020\Fatture\",D19," Trimestre\",B19,".pdf")) -> #REF! | J19: =IF(I19<>"","x","") | R19: Imponibile | S19: =0.78*S17 -> 21996
A20: 16 | E20: =IF(#REF!="CASA",CONCATENATE("C:\Users\studi\Google Drive\CONTABILITA'\2020\Fatture\",D20," Trimestre\",B20,".pdf"),CONCATENATE("C:\Users\Sebastiano\Google Drive\CONTABILITA'\2020\Fatture\",D20," Trimestre\",B20,".pdf")) -> #REF! | J20: =IF(I20<>"","x","") | R20: Imposta sostitutiva (15% al fisco) | S20: =0.15*S19 -> 3299.4
A21: 17 | E21: =IF(#REF!="CASA",CONCATENATE("C:\Users\studi\Google Drive\CONTABILITA'\2020\Fatture\",D21," Trimestre\",B21,".pdf"),CONCATENATE("C:\Users\Sebastiano\Google Drive\CONTABILITA'\2020\Fatture\",D21," Trimestre\",B21,".pdf")) -> #REF! | J21: =IF(I21<>"","x","")
A22: 18 | E22: =IF(#REF!="CASA",CONCATENATE("C:\Users\studi\Google Drive\CONTABILITA'\2020\Fatture\",D22," Trimestre\",B22,".pdf"),CONCATENATE("C:\Users\Sebastiano\Google Drive\CONTABILITA'\2020\Fatture\",D22," Trimestre\",B22,".pdf")) -> #REF! | J22: =IF(I22<>"","x","") | R22: INARCASSA
A23: 19 | E23: =IF(#REF!="CASA",CONCATENATE("C:\Users\studi\Google Drive\CONTABILITA'\2020\Fatture\",D23," Trimestre\",B23,".pdf"),CONCATENATE("C:\Users\Sebastiano\Google Drive\CONTABILITA'\2020\Fatture\",D23," Trimestre\",B23,".pdf")) -> #REF! | J23: =IF(I23<>"","x","") | R23: Contributo soggettivo | S23: =MAX(780,0.0725*S19) -> 1594.71
A24: 20 | E24: =IF(#REF!="CASA",CONCATENATE("C:\Users\studi\Google Drive\CONTABILITA'\2020\Fatture\",D24," Trimestre\",B24,".pdf"),CONCATENATE("C:\Users\Sebastiano\Google Drive\CONTABILITA'\2020\Fatture\",D24," Trimestre\",B24,".pdf")) -> #REF! | J24: =IF(I24<>"","x","") | R24: Contributo integrativo | S24: =MAX(231.5,0.04*S16) -> 1128
A25: 21 | E25: =IF(#REF!="CASA",CONCATENATE("C:\Users\studi\Google Drive\CONTABILITA'\2020\Fatture\",D25," Trimestre\",B25,".pdf"),CONCATENATE("C:\Users\Sebastiano\Google Drive\CONTABILITA'\2020\Fatture\",D25," Trimestre\",B25,".pdf")) -> #REF! | J25: =IF(I25<>"","x","") | R25: Contributo maternità | S25: 39
K26: totale fatturato | L26: =SUBTOTAL(9,L5:L25) -> 28200 | N26: =SUBTOTAL(9,N5:N25) -> 1128 | O26: TOT | P26: =SUBTOTAL(9,P5:P25) -> 29328 | S26: =SUM(S23:S25) -> 2761.71
K27: totale incassato | L27: =SUMIF(J5:J25,"x",L5:L25) -> 28200 | S27: =(P26-S28)/P26 -> 0.20666633 | T27: =1-(L26-S20-S23-S25)/L26 -> 0.17493298
R28: Netto totale | S28: =P26-S20-S26 -> 23266.89 | T28: =S34*T7+S32*S7+S31+S33 -> #DIV/0!
R29: Netto 2020 | S29: =S34*T7+S33 -> 23266.89
R31: Netto Mattia | S31: =(SUM(P17)-(S20+S26)/(P26)*SUM(P17)) -> 0
P32: =(S34*T7+S32*S7+S33)/(S7+T7) -> #DIV/0! | Q32: Media | R32: Netto mensile anno prec | S32: =(SUM(Z5:Z6)*1.04-(S20+S26)/(P26)*SUM(Z5:Z6)*1.04)/S7 -> #DIV/0!
R33: Netto Andrea | S33: =(SUM(P18)-(S20+S26)/(P26)*SUM(P18)) -> 0 | T33: Media | U33: =(S34*T7+S33)/T7 -> 1938.9075
R34: Netto mensile anno attuale | S34: =(P26-SUM(Z5:Z6)*1.04-P17-P18-(S20+S26)/(P26)*(P26-SUM(Z5:Z6)*1.04-P17-P18))/T7 -> 1938.9075
R35: Controllo | S35: =S34*T7+S32*S7+S26+S20+S31+S33 -> #DIV/0!

Sheet 2024 reale
C1: ELENCO FATTURE
C2: Anno 2023 | J2: Anno 2017
B4: Numero | C4: NOTE | E4: Mese | G4: Data emissione | H4: Destinatario | I4: Netto | J4: Iva | K4: Integr. 4% | L4: Bollo | M4: Totale | N4: Estero
B5: 14 | D5: 45291 | E5: Dicembre | H5: STI | I5: 2900 | J5: 0 | K5: =IF(N5="x",0,0.04*(L5+I5)) -> 0 | L5: 2 | M5: =I5+K5+L5 -> 2902 | N5: x | O5: =M5*(1-Q27) -> 2408.9609 | P5: =O5-M5 -> -493.03913
B6: 1 | D6: 45322 | E6: Gennaio | F6: =IF(#REF!="CASA",CONCATENATE("C:\Users\studi\Google Drive\CONTABILITA'\",D6,"\",E6," Trimestre\Fatture\",C6,".pdf"),CONCATENATE("C:\Users\Sebastiano\Google Drive\CONTABILITA'\",D6,"\",E6," Trimestre\Fatture\",C6,".pdf")) -> #REF! | H6: STI | I6: 2900 | J6: 0 | K6: =IF(N6="x",0,0.04*(L6+I6)) -> 0 | L6: 2 | M6: =I6+K6+L6 -> 2902 | N6: x
B7: 2 | D7: 45351 | E7: Febbraio | F7: =IF(#REF!="CASA",CONCATENATE("C:\Users\studi\Google Drive\CONTABILITA'\2019\",E7," Trimestre\Fatture\",C7,".pdf"),CONCATENATE("C:\Users\Sebastiano\Google Drive\CONTABILITA'\2019\",E7," Trimestre\Fatture\",C7,".pdf")) -> #REF! | H7: STI | I7: 2900 | J7: 0 | K7: =IF(N7="x",0,0.04*(L7+I7)) -> 0 | L7: 2 | M7: =I7+K7+L7 -> 2902 | N7: x
B8: 3 | D8: 45382 | E8: Marzo | F8: =IF(#REF!="CASA",CONCATENATE("C:\Users\studi\Google Drive\CONTABILITA'\2020\",E8," Trimestre\Fatture\",C8,".pdf"),CONCATENATE("C:\Users\Sebastiano\Google Drive\CONTABILITA'\2020\",E8," Trimestre\Fatture\",C8,".pdf")) -> #REF! | H8: STI | I8: 2900 | J8: 0 | K8: =IF(N8="x",0,0.04*(L8+I8)) -> 0 | L8: 2 | M8: =I8+K8+L8 -> 2902 | N8: x
B9: 4 | D9: 45390 | H9: Nardini | I9: 1500 | J9: 0 | K9: =IF(N9="x",0,0.04*(L9+I9)) -> 60.08 | L9: 2 | M9: =I9+K9+L9 -> 1562.08
B10: 5 | D10: 45412 | E10: Aprile | F10: =IF(#REF!="CASA",CONCATENATE("C:\Users\studi\Google Drive\CONTABILITA'\2020\Fatture\",E10," Trimestre\",C10,".pdf"),CONCATENATE("C:\Users\Sebastiano\Google Drive\CONTABILITA'\2020\Fatture\",E10," Trimestre\",C10,".pdf")) -> #REF! | H10: STI | I10: 2900 | J10: 0 | K10: =IF(N10="x",0,0.04*(L10+I10)) -> 0 | L10: 2 | M10: =I10+K10+L10 -> 2902 | N10: x | S10: =55+1.3+2.9+0.35+2+0.7+5-2.15 -> 65.1
B11: 6 | D11: 45443 | E11: Maggio | F11: =IF(#REF!="CASA",CONCATENATE("C:\Users\studi\Google Drive\CONTABILITA'\2020\Fatture\",E11," Trimestre\",C11,".pdf"),CONCATENATE("C:\Users\Sebastiano\Google Drive\CONTABILITA'\2020\Fatture\",E11," Trimestre\",C11,".pdf")) -> #REF! | H11: STI | I11: 2900 | J11: 0 | K11: =IF(N11="x",0,0.04*(L11+I11)) -> 0 | L11: 2 | M11: =I11+K11+L11 -> 2902 | N11: x
B12: 7 | D12: 45473 | E12: Giugno | F12: =IF(#REF!="CASA",CONCATENATE("C:\Users\studi\Google Drive\CONTABILITA'\2020\Fatture\",E12," Trimestre\",C12,".pdf"),CONCATENATE("C:\Users\Sebastiano\Google Drive\CONTABILITA'\2020\Fatture\",E12," Trimestre\",C12,".pdf")) -> #REF! | H12: STI | I12: 2900 | J12: 0 | K12: =IF(N12="x",0,0.04*(L12+I12)) -> 116.08 | L12: 2 | M12: =I12+K12+L12 -> 3018.08 | O12: =M12-M11 -> 116.08 | Q12: Coefficiente ATECO | S12: 0.78
B13: 8 | D13: 45504 | E13: Luglio | F13: =IF(#REF!="CASA",CONCATENATE("C:\Users\studi\Google Drive\CONTABILITA'\2020\Fatture\",E13," Trimestre\",C13,".pdf"),CONCATENATE("C:\Users\Sebastiano\Google Drive\CONTABILITA'\2020\Fatture\",E13," Trimestre\",C13,".pdf")) -> #REF! | H13: STI | I13: 2900 | J13: 0 | K13: =IF(N13="x",0,0.04*(L13+I13)) -> 116.08 | L13: 2 | M13: =I13+K13+L13 -> 3018.08
B14: 9 | D14: 45535 | E14: Agosto | F14: =IF(#REF!="CASA",CONCATENATE("C:\Users\studi\Google Drive\CONTABILITA'\2020\Fatture\",E14," Trimestre\",C14,".pdf"),CONCATENATE("C:\Users\Sebastiano\Google Drive\CONTABILITA'\2020\Fatture\",E14," Trimestre\",C14,".pdf")) -> #REF! | H14: STI | I14: 2900 | J14: 0 | K14: =IF(N14="x",0,0.04*(L14+I14)) -> 116.08 | L14: 2 | M14: =I14+K14+L14 -> 3018.08 | Q14: forfettario
B15: 10 | D15: 45565 | E15: Settembre | F15: =IF(#REF!="CASA",CONCATENATE("C:\Users\studi\Google Drive\CONTABILITA'\2020\Fatture\",E15," Trimestre\",C15,".pdf"),CONCATENATE("C:\Users\Sebastiano\Google Drive\CONTABILITA'\2020\Fatture\",E15," Trimestre\",C15,".pdf")) -> #REF! | H15: STI | I15: =2900+27.2*2+13.6 -> 2968 | J15: 0 | K15: =IF(N15="x",0,0.04*(L15+I15)) -> 118.8 | L15: 2 | M15: =I15+K15+L15 -> 3088.8 | P15: Totale fatturato annuo | Q15: =I26 -> 42497
B16: 11 | D16: 45567 | F16: =IF(#REF!="CASA",CONCATENATE("C:\Users\studi\Google Drive\CONTABILITA'\2020\Fatture\",E16," Trimestre\",C16,".pdf"),CONCATENATE("C:\Users\Sebastiano\Google Drive\CONTABILITA'\2020\Fatture\",E16," Trimestre\",C16,".pdf")) -> #REF! | H16: Gosparini | I16: 350 | J16: 0 | K16: =IF(N16="x",0,0.04*(L16+I16)) -> 14.08 | L16: 2 | M16: =I16+K16+L16 -> 366.08 | P16: volume d'affari compessivo | Q16: =Q15+SUM(L5:L24) -> 42533
B17: 12 | D17: 45580 | F17: =IF(#REF!="CASA",CONCATENATE("C:\Users\studi\Google Drive\CONTABILITA'\2020\Fatture\",E17," Trimestre\",C17,".pdf"),CONCATENATE("C:\Users\Sebastiano\Google Drive\CONTABILITA'\2020\Fatture\",E17," Trimestre\",C17,".pdf")) -> #REF! | H17: Bliz | I17: 2000 | J17: 0 | K17: =IF(N17="x",0,0.04*(L17+I17)) -> 80.08 | L17: 2 | M17: =I17+K17+L17 -> 2082.08 | P17: Spese deducibili | R17: =R18/0.78 -> 37924.359 | S17: LIMITE
B18: 13 | D18: 45626 | E18: Ottobre | F18: =IF(#REF!="CASA",CONCATENATE("C:\Users\studi\Google Drive\CONTABILITA'\2020\Fatture\",E18," Trimestre\",C18,".pdf"),CONCATENATE("C:\Users\Sebastiano\Google Drive\CONTABILITA'\2020\Fatture\",E18," Trimestre\",C18,".pdf")) -> #REF! | H18: STI | I18: =2900+25.5+25.5 -> 2951 | J18: 0 | K18: =IF(N18="x",0,0.04*(L18+I18)) -> 118.12 | L18: 2 | M18: =I18+K18+L18 -> 3071.12 | P18: Imponibile | Q18: =0.78*Q16 -> 33175.74 | R18: 29581 | S18: 39000 | T18: Già pagato | U18: Da pagare
B19: 14 | D19: 45596 | E19: Novembre | F19: =IF(#REF!="CASA",CONCATENATE("C:\Users\studi\Google Drive\CONTABILITA'\2020\Fatture\",E19," Trimestre\",C19,".pdf"),CONCATENATE("C:\Users\Sebastiano\Google Drive\CONTABILITA'\2020\Fatture\",E19," Trimestre\",C19,".pdf")) -> #REF! | H19: Morgante | I19: 1280 | J19: 0 | K19: =IF(N19="x",0,0.04*(L19+I19)) -> 51.28 | L19: 2 | M19: =I19+K19+L19 -> 1333.28 | P19: Imposta sostitutiva (15% al fisco) | Q19: =0.15*(Q18-Q25) -> 4454.0488 | R19: =0.15*(R18-Q25) -> 3914.8378 | S19: Extra | T19: =1854+2148.2 -> 4002.2 | U19: 0
B20: 15 | D20: 45626 | E20: Novembre | F20: =IF(#REF!="CASA",CONCATENATE("C:\Users\studi\Google Drive\CONTABILITA'\2020\Fatture\",E20," Trimestre\",C20,".pdf"),CONCATENATE("C:\Users\Sebastiano\Google Drive\CONTABILITA'\2020\Fatture\",E20," Trimestre\",C20,".pdf")) -> #REF! | H20: STI | I20: 2900 | J20: 0 | K20: =IF(N20="x",0,0.04*(L20+I20)) -> 116.08 | L20: 2 | M20: =I20+K20+L20 -> 3018.08 | S20: =(S18-Q18)/0.78 -> 7467
B21: 16 | D21: 45638 | F21: =IF(#REF!="CASA",CONCATENATE("C:\Users\studi\Google Drive\CONTABILITA'\2020\Fatture\",E21," Trimestre\",C21,".pdf"),CONCATENATE("C:\Users\Sebastiano\Google Drive\CONTABILITA'\2020\Fatture\",E21," Trimestre\",C21,".pdf")) -> #REF! | H21: Gosparini | I21: 450 | J21: 0 | K21: =IF(N21="x",0,0.04*(L21+I21)) -> 18.08 | L21: 2 | M21: =I21+K21+L21 -> 470.08 | P21: INARCASSA | S21: Ridotto | T21: Già pagato | U21: Da pagare
H22: Valent | I22: =48+1950 -> 1998 | J22: 0 | K22: =IF(N22="x",0,0.04*(L22+I22)) -> 80 | L22: 2 | M22: =I22+K22+L22 -> 2080 | P22: Contributo soggettivo | Q22: =MAX(780,0.0725*Q18)*IF(S22="Sì",1,2) -> 2405.2411 | S22: =IF(S20>0,"Sì","No") -> Sì | T22: 615 | U22: =Q22-T22 -> 1790.2411
P23: Contributo integrativo | Q23: =MAX(231.5,K25) -> 1004.84 | T23: 627 | U23: =Q23-T23 -> 377.84
P24: Contributo maternità | Q24: 72 | T24: =1506.76+733.34 -> 2240.1 | U24: =Q24-T24 -> -2168.1
H25: totale fatturato | I25: =SUBTOTAL(9,I5:I24) -> 42497 | K25: =SUBTOTAL(9,K5:K24) -> 1004.84 | L25: TOT | M25: =SUBTOTAL(9,M5:M24) -> 43537.84 | Q25: =SUM(Q22:Q24) -> 3482.0811 | T25: =SUM(T22:T24) -> 3482.1 | U25: =SUM(U22:U24) -> -0.01885
H26: totale incassato | I26: =SUM(I5:I24) -> 42497
Q27: =(M25-Q28)/M25 -> 0.16989632 | S27: =1-(I25-R19-Q22-Q24)/I25 -> 0.15041248
P28: Netto totale | Q28: =M25-R19-Q25 -> 36140.921
P30: Netto mensile anno attuale | Q30: =Q28/12 -> 3011.7434 | T30: Rimanente 2024 | U30: =U25+U19 -> -0.01885 | V30: =SUMIFS(M5:M19,D5:D19,"<"&TODAY())/M25*(Q19+Q25)-T25-T19 -> -563.14094
P31: Netto mensile 13 mensilità | Q31: =Q30/13*12 -> 2780.0708 | T31: Anno precedente | U31: ='2023 reale'!T31 -> 0 | V31: =U31+V30 -> -563.14094
G33: A1 | H33: =H34*0.78*0+26639 -> 26639 | I33: preso dal commericalista LM22 colonna 5
G34: B1 | H34: =(SUM(I5:I29)+SUM(L5:L29))*0+34152 -> 34152 | I34: preso dal commericalista LM22 colonna 3
G35: B2.1 | H35: =SUMIFS(I5:I24,N5:N24,I35)+SUMIFS(L5:L24,N5:N24,I35) -> 25121 | I35: =""
G36: B5.1 | H36: =SUMIFS(I5:I24,N5:N24,I36)+SUMIFS(L5:L24,N5:N24,I36) -> 17412 | I36: x | J36: CHECK!
G37: B7.1 | H37: =H35 -> 25121 | J37: =H34-H35-H36 -> -8381 | K37: <1€
G38: E1 | H38: =K26 -> 0

Sheet 2025 reale
G2: Anno 2017
B3: Numero | C3: Girorno emissione | D3: Mese | E3: Destinatario | F3: Netto | G3: Iva | H3: Integr. 4% | I3: Bollo | J3: Totale | K3: Estero? | L3: Lavorati reali | M3: Giorni lavorativi | N3: Ferie / malattia | O3: Extra week | P3: Spostati dal mese precedente
B4: 17 | C4: 45646 | D4: Dicembre | E4: STI | F4: =2900+13.6*2 -> 2927.2 | G4: 0 | H4: =IF(K4="x",0,0.04*(I4+F4)) -> 117.168 | I4: 2 | J4: =F4+H4+I4 -> 3046.368 | L4: =M4-N4+O4 -> 20 | M4: 20
B5: 1 | C5: 45688 | D5: Gennaio | E5: STI | F5: =2900+1.7+25.5+25.5 -> 2952.7 | G5: 0 | H5: =IF(K5="x",0,0.04*(I5+F5)) -> 118.188 | I5: 2 | J5: =F5+H5+I5 -> 3072.888 | L5: =M5-N5+O5 -> 21 | M5: 21
B6: 2 | C6: 45716 | D6: Febbraio | E6: STI | F6: =2900+54.4 -> 2954.4 | G6: 0 | H6: =IF(K6="x",0,0.04*(I6+F6)) -> 118.256 | I6: 2 | J6: =F6+H6+I6 -> 3074.656 | L6: =M6-N6+O6 -> 20 | M6: 20
B7: 3 | C7: 45737 | D7: Marzo | E7: Valent | F7: 50 | G7: 0 | H7: =IF(K7="x",0,0.04*(I7+F7)) -> 2.08 | I7: 2 | J7: =F7+H7+I7 -> 54.08 | R7: Prezzo giornaliero | S7: 165
B8: 4 | C8: 45747 | D8: Marzo | E8: STI | F8: =13.6+2900 -> 2913.6 | G8: 0 | H8: =IF(K8="x",0,0.04*(I8+F8)) -> 116.624 | I8: 2 | J8: =F8+H8+I8 -> 3032.224 | L8: =M8-N8+O8 -> 21 | M8: 21
B9: 5 | C9: 45777 | D9: Aprile | E9: STI | F9: =2900+15.06*2 -> 2930.12 | G9: 0 | H9: =IF(K9="x",0,0.04*(I9+F9)) -> 117.2848 | I9: 2 | J9: =F9+H9+I9 -> 3049.4048 | L9: =M9-N9+O9 -> 20 | M9: 20
B10: 6 | C10: 45789 | D10: Maggio | E10: ProLoco | F10: 748 | G10: 0 | H10: =IF(K10="x",0,0.04*(I10+F10)) -> 30 | I10: 2 | J10: =F10+H10+I10 -> 780
B11: 7 | C11: 45808 | D11: Maggio | E11: STI | F11: =2900+15.06*2 -> 2930.12 | G11: 0 | H11: =IF(K11="x",0,0.04*(I11+F11)) -> 117.2848 | I11: 2 | J11: =F11+H11+I11 -> 3049.4048 | L11: =M11-N11+O11 -> 21 | M11: 21 | R11: Coefficiente ATECO | S11: 0.78
B12: 8 | C12: 45829 | D12: Giugno | E12: Pagnacco | F12: =2000+16*3 -> 2048 | G12: 0 | H12: =IF(K12="x",0,0.04*(I12+F12)) -> 82 | I12: 2 | J12: =F12+H12+I12 -> 2132 | S12: forfettario
B13: 9 | C13: 45838 | D13: Giugno | E13: STI | F13: =L13*$S$7 -> 3300 | G13: 0 | H13: =IF(K13="x",0,0.04*(I13+F13)) -> 132.08 | I13: 2 | J13: =F13+H13+I13 -> 3434.08 | L13: =M13-N13+O13 -> 20 | M13: 20 | R13: Totale fatturato annuo | S13: =F27 -> 43834.14
B14: 10 | C14: 45869 | D14: Luglio | E14: STI | F14: =L14*$S$7 -> 3795 | G14: 0 | H14: =IF(K14="x",0,0.04*(I14+F14)) -> 151.88 | I14: 2 | J14: =F14+H14+I14 -> 3948.88 | L14: =M14-N14+O14 -> 23 | M14: 23 | R14: volume d'affari compessivo | S14: =S13+SUM(I4:I25) -> 43918.14
B15: 11 | C15: 45900 | D15: Agosto | E15: STI | F15: =L15*$S$7 -> 2145 | G15: 0 | H15: =IF(K15="x",0,0.04*(I15+F15)) -> 85.88 | I15: 2 | J15: =F15+H15+I15 -> 2232.88 | L15: =M15-N15+O15 -> 13 | M15: 20 | N15: 10 | O15: 3 | R15: Spese deducibili
B16: 12 | C16: 45930 | D16: Settembre | E16: STI | F16: =L16*$S$7 -> 3630 | G16: 0 | H16: =IF(K16="x",0,0.04*(I16+F16)) -> 145.28 | I16: 2 | J16: =F16+H16+I16 -> 3777.28 | L16: =M16-N16+O16 -> 22 | M16: 22 | R16: Imponibile | S16: =0.78*S14 -> 34256.149
B17: 13 | C17: 45938 | D17: Ottobre | E17: ERA | F17: 1300 | G17: 1 | H17: =IF(K17="x",0,0.04*(I17+F17)) -> 52.08 | I17: 2 | J17: =F17+H17+I17 -> 1354.08
B18: 14 | C18: 45938 | D18: Ottobre | E18: Gosparini costruz | F18: 350 | G18: 2 | H18: =IF(K18="x",0,0.04*(I18+F18)) -> 14.08 | I18: 2 | J18: =F18+H18+I18 -> 366.08
B19: 15 | C19: 45961 | D19: Ottobre | E19: STI | F19: =L19*$S$7 -> 4125 | G19: 0 | H19: =IF(K19="x",0,0.04*(I19+F19)) -> 165.08 | I19: 2 | J19: =F19+H19+I19 -> 4292.08 | L19: =M19-N19+O19 -> 25 | M19: 23 | O19: 2 | R19: Imposta sostitutiva (15% al fisco) | S19: =0.15*(S16-S26) -> 4491.5779 | U19: Già pagato | V19: Da pagare
B20: 16 | C20: 45991 | D20: Novembre | E20: STI | F20: =L20*$S$7 -> 3135 | G20: 0 | H20: =IF(K20="x",0,0.04*(I20+F20)) -> 125.48 | I20: 2 | J20: =F20+H20+I20 -> 3262.48 | L20: =M20-N20+O20 -> 19 | M20: 20 | N20: 1 | U20: =(449+318)*0+1842 -> 1842 | V20: =S19-U20 -> 2649.5779
B21: 17 | C21: 45992 | D21: Dicembre | E21: Schirmer | F21: 1600 | H21: =IF(K21="x",0,0.04*(I21+F21)) -> 66 | I21: 50 | J21: =F21+H21+I21 -> 1716 | T21: LIMITE
R22: INARCASSA | T22: 39000 | U22: Già pagato | V22: Da pagare
R23: Contributo soggettivo | S23: =MAX(780,0.0725*S16)*IF(T26="Sì",1,2) -> 2483.5708 | T23: Extra | U23: 633.5 | V23: =S23-U23 -> 1850.0708
R24: Contributo integrativo | S24: =MAX(231.5,H26) -> 1756.7256 | T24: =(T22-S16)/0.78 -> 6081.86 | U24: 652.5 | V24: =S24-U24 -> 1104.2256
R25: Contributo maternità | S25: 72 | T25: Ridotto | V25: =S25-U25 -> 72
E26: totale fatturato | F26: =SUBTOTAL(9,F4:F25) -> 43834.14 | H26: =SUBTOTAL(9,H4:H25) -> 1756.7256 | I26: TOT | J26: =SUBTOTAL(9,J4:J25) -> 45674.866 | L26: =SUM(L13:L20) -> 122 | M26: =SUM(M4:M20) -> 251 | S26: =SUM(S23:S25) -> 4312.2964 | T26: =IF(T24>0,"Sì","No") -> Sì | U26: =SUM(U23:U25) -> 1286 | V26: =SUM(V23:V25) -> 3026.2964
E27: totale incassato | F27: =SUM(F4:F25) -> 43834.14 | L27: =SUM(L4:L21) -> 245
S28: =(J26-S29)/J26 -> 0.19275096 | U28: =1-(F26-S19-S23-S25)/F26 -> 0.1607685
R29: Netto totale | S29: =J26-S19-S26 -> 36870.991
R31: Netto mensile anno attuale | S31: =S29/12 -> 3072.5826 | V31: Rimanente 2025 | W31: =V26+V20 -> 5675.8743 | X31: =SUMIFS(J4:J21,C4:C21,"<"&TODAY())/J26*(S19+S26)-U26-U20 -> 5675.8743
L32: Tasse ad oggi | N32: =(S19+S26)*SUM(J4:J12)/J26-U26+'2024 reale'!U25 -> 2817.8468 | R32: Netto mensile 13 mensilità | S32: =S31/13*12 -> 2836.2301 | V32: Anno precedente | W32: ='2024 reale'!U19+'2024 reale'!U25 -> -0.01885 | X32: =W32+X31 -> 5675.8555
R34: A1 | S34: =S35*0.78*0+26639 -> 26639 | T34: preso dal commericalista LM22 colonna 5
R35: B1 | S35: =(SUM(F4:F30)+SUM(I4:I30))*0+34152 -> 34152 | T35: preso dal commericalista LM22 colonna 3
R36: B2.1 | S36: =SUMIFS(F4:F25,K4:K25,T36)+SUMIFS(I4:I25,K4:K25,T36) -> 43918.14 | T36: =""
R37: B5.1 | S37: =SUMIFS(F4:F25,K4:K25,T37)+SUMIFS(I4:I25,K4:K25,T37) -> 0 | T37: x | U37: CHECK!
R38: B7.1 | S38: =S36 -> 43918.14 | U38: =S35-S36-S37 -> -9766.14 | V38: <1€
R39: E1 | S39: =H27 -> 0

Sheet 2026 reale
C1: ELENCO FATTURE
C2: Anno 2025 | H2: Anno 2017
B3: Numero | C3: Emessa? | D3: Girorno emissione | E3: Mese | F3: Destinatario | G3: Netto | H3: Iva | I3: Integr. 4% | J3: Bollo | K3: Totale | L3: Estero? | M3: Lavorati reali | N3: Giorni lavorativi | O3: Ferie / malattia | P3: Extra week | Q3: Spostati dal mese precedente
B4: 17 | D4: 46022 | E4: Dicembre | F4: STI | G4: =M4*$T$7 -> 2145 | H4: 0 | I4: =IF(L4="x",0,0.04*(J4+G4)) -> 85.88 | J4: 2 | K4: =G4+I4+J4 -> 2232.88 | M4: =N4-O4+P4 -> 13 | N4: 20 | O4: 7
B5: 1 | D5: 46053 | E5: Gennaio | F5: STI | G5: =M5*$T$7 -> 3135 | H5: 0 | I5: =IF(L5="x",0,0.04*(J5+G5)) -> 125.48 | J5: 2 | K5: =G5+I5+J5 -> 3262.48 | M5: =N5-O5+P5+Q5 -> 19 | N5: 21 | O5: 3 | Q5: 1
B6: 2 | D6: 46081 | E6: Febbraio | F6: STI | G6: =M6*$T$7 -> 3135 | H6: 0 | I6: =IF(L6="x",0,0.04*(J6+G6)) -> 125.48 | J6: 2 | K6: =G6+I6+J6 -> 3262.48 | M6: =N6-O6+P6+Q6 -> 19 | N6: 20 | O6: 1.5 | Q6: 0.5
B7: 3 | D7: 46112 | E7: Marzo | F7: STI | G7: =M7*$T$7 -> 3465 | H7: 0 | I7: =IF(L7="x",0,0.04*(J7+G7)) -> 138.68 | J7: 2 | K7: =G7+I7+J7 -> 3605.68 | M7: =N7-O7+P7+Q7 -> 21 | N7: 21 | S7: Prezzo giornaliero | T7: 165
B8: 4 | D8: 46146 | E8: Aprile | F8: Cigliani | G8: 5000 | H8: 0 | I8: =IF(L8="x",0,0.04*(J8+G8)) -> 200.08 | J8: 2 | K8: =G8+I8+J8 -> 5202.08 | S8: Prezzo giornaliero dal 01/06 | T8: 180
B9: 5 | D9: 46142 | E9: Aprile | F9: STI | G9: =M9*$T$7 -> 2970 | H9: 0 | I9: =IF(L9="x",0,0.04*(J9+G9)) -> 118.88 | J9: 2 | K9: =G9+I9+J9 -> 3090.88 | M9: =N9-O9+P9+Q9 -> 18 | N9: 20 | O9: 2.5 | Q9: 0.5
B10: 7 | D10: 46173 | E10: Maggio | F10: STI | G10: =M10*$T$7 -> 3217.5 | H10: 0 | I10: =IF(L10="x",0,0.04*(J10+G10)) -> 128.78 | J10: 2 | K10: =G10+I10+J10 -> 3348.28 | M10: =N10-O10+P10+Q10 -> 19.5 | N10: 21 | O10: 1.5
B11: 9 | D11: 46203 | E11: Giugno | F11: STI | G11: =M11*$T$8 -> 3510 | H11: 0 | I11: =IF(L11="x",0,0.04*(J11+G11)) -> 140.48 | J11: 2 | K11: =G11+I11+J11 -> 3652.48 | M11: =N11-O11+P11+Q11 -> 19.5 | N11: 20 | O11: 0.5 | S11: Coefficiente ATECO | T11: 0.78
B12: 10 | D12: 46234 | E12: Luglio | F12: STI | G12: =M12*$T$8 -> 4230 | H12: 0 | I12: =IF(L12="x",0,0.04*(J12+G12)) -> 169.28 | J12: 2 | K12: =G12+I12+J12 -> 4401.28 | M12: =N12-O12+P12+Q12 -> 23.5 | N12: 23 | P12: 0.5 | T12: forfettario
B13: 11 | D13: 46265 | E13: Agosto | F13: STI | G13: =M13*$T$8 -> 1800 | H13: 0 | I13: =IF(L13="x",0,0.04*(J13+G13)) -> 72.08 | J13: 2 | K13: =G13+I13+J13 -> 1874.08 | M13: =N13-O13+P13+Q13 -> 10 | N13: 20 | O13: 10 | S13: Totale fatturato annuo | T13: =G21 -> 44487.5
B14: 12 | D14: 46295 | E14: Settembre | F14: STI | G14: =M14*$T$8 -> 4050 | H14: 0 | I14: =IF(L14="x",0,0.04*(J14+G14)) -> 162.08 | J14: 2 | K14: =G14+I14+J14 -> 4214.08 | M14: =N14-O14+P14+Q14 -> 22.5 | N14: 22 | P14: 0.5 | S14: volume d'affari compessivo | T14: =T13+SUM(J4:J19) -> 44513.5
B15: 13 | D15: 46326 | E15: Ottobre | F15: STI | G15: =M15*$T$8 -> 4140 | H15: 0 | I15: =IF(L15="x",0,0.04*(J15+G15)) -> 165.68 | J15: 2 | K15: =G15+I15+J15 -> 4307.68 | M15: =N15-O15+P15+Q15 -> 23 | N15: 23 | S15: Spese deducibili
B16: 14 | D16: 46356 | E16: Novembre | F16: STI | G16: =M16*$T$8 -> 3690 | H16: 0 | I16: =IF(L16="x",0,0.04*(J16+G16)) -> 147.68 | J16: 2 | K16: =G16+I16+J16 -> 3839.68 | M16: =N16-O16+P16+Q16 -> 20.5 | N16: 20 | P16: 0.5 | S16: Imponibile | T16: =0.78*T14 -> 34720.53
S19: Imposta sostitutiva (15% al fisco) | T19: =0.15*(T16-T26) -> 4175.027 | V19: Già pagato | W19: Da pagare
F20: totale fatturato | G20: =SUBTOTAL(9,G4:G19) -> 44487.5 | I20: =SUBTOTAL(9,I4:I19) -> 1780.54 | J20: TOT | K20: =SUBTOTAL(9,K4:K19) -> 46294.04 | M20: =SUM(M4:M16) -> 228.5 | N20: =SUM(N4:N15) -> 231 | W20: =T19-V20 -> 4175.027
F21: totale incassato | G21: =SUM(G4:G19) -> 44487.5 | M21: =SUM(M4:M15) -> 208
S22: INARCASSA | V22: Già pagato | W22: Da pagare
S23: Contributo soggettivo | T23: =MAX(780,0.0725*T16)*IF(U26="Sì",1,2) -> 5034.4768 | V23: 1863 | W23: =T23-V23 -> 3171.4768
S24: Contributo integrativo | T24: =MAX(231.5,I20) -> 1780.54 | W24: =T24-V24 -> 1780.54
N25: hydr | S25: Contributo maternità | T25: 72 | U25: Ridotto | W25: =T25-V25 -> 72
M26: Tasse ad oggi | O26: =(T19+T26)*SUM(K4:K9)/K20-V26+'2024 reale'!U25 -> 3072.8841 | T26: =SUM(T23:T25) -> 6887.0168 | U26: No | V26: =SUM(V23:V25) -> 1863 | W26: =SUM(W23:W25) -> 5024.0168
T28: =(K20-T29)/K20 -> 0.23895179 | V28: =1-(G20-T19-T23-T25)/G20 -> 0.20863172
S29: Netto totale | T29: =K20-T19-T26 -> 35231.996
S31: Netto mensile anno attuale | T31: =T29/12 -> 2935.9997 | W31: Rimanente 2026 | X31: =W26+W20 -> 9199.0438 | Y31: =SUMIFS(K4:K15,D4:D15,"<"&TODAY())/K20*(T19+T26)-V26-V20 -> 4745.7471
S32: Netto mensile 13 mensilità | T32: =T31/13*12 -> 2710.1536 | W32: Anno precedente | X32: ='2025 reale'!X32 -> 5675.8555 | Y32: =X32+Y31 -> 10421.603

Sheet 2027 bozza
C1: ELENCO FATTURE
C2: Anno 2025 | H2: Anno 2017
B3: Numero | C3: Emessa? | D3: Girorno emissione | E3: Mese | F3: Destinatario | G3: Netto | H3: Iva | I3: Integr. 4% | J3: Bollo | K3: Totale | L3: Estero? | M3: Lavorati reali | N3: Giorni lavorativi | O3: Ferie / malattia | P3: Extra week | Q3: Spostati dal mese precedente
B4: 17 | D4: 46022 | E4: Dicembre | F4: STI | G4: =M4*$T$7 -> 2880 | H4: 0 | I4: =IF(L4="x",0,0.04*(J4+G4)) -> 115.28 | J4: 2 | K4: =G4+I4+J4 -> 2997.28 | M4: =N4-O4+P4 -> 16 | N4: 20 | O4: 4 | Q4: 0.5 | R4: da novembre
B5: 1 | D5: 46053 | E5: Gennaio | F5: STI | G5: =M5*$T$7 -> 3780 | H5: 0 | I5: =IF(L5="x",0,0.04*(J5+G5)) -> 151.28 | J5: 2 | K5: =G5+I5+J5 -> 3933.28 | M5: =N5-O5+P5 -> 21 | N5: 21
B6: 2 | D6: 46081 | E6: Febbraio | F6: STI | G6: =M6*$T$7 -> 3690 | H6: 0 | I6: =IF(L6="x",0,0.04*(J6+G6)) -> 147.68 | J6: 2 | K6: =G6+I6+J6 -> 3839.68 | M6: =N6-O6+P6 -> 20.5 | N6: 20 | P6: 0.5
B7: 4 | D7: 46112 | E7: Marzo | F7: STI | G7: =M7*$T$7 -> 3870 | H7: 0 | I7: =IF(L7="x",0,0.04*(J7+G7)) -> 154.88 | J7: 2 | K7: =G7+I7+J7 -> 4026.88 | M7: =N7-O7+P7 -> 21.5 | N7: 21 | P7: 0.5 | S7: Prezzo giornaliero | T7: 180
B8: 5 | D8: 46142 | E8: Aprile | F8: STI | G8: =M8*$T$7 -> 3600 | H8: 0 | I8: =IF(L8="x",0,0.04*(J8+G8)) -> 144.08 | J8: 2 | K8: =G8+I8+J8 -> 3746.08 | M8: =N8-O8+P8 -> 20 | N8: 20 | S8: Prezzo giornaliero dal 01/06 | T8: 200
B9: 7 | D9: 46173 | E9: Maggio | F9: STI | G9: =M9*$T$7 -> 3870 | H9: 0 | I9: =IF(L9="x",0,0.04*(J9+G9)) -> 154.88 | J9: 2 | K9: =G9+I9+J9 -> 4026.88 | M9: =N9-O9+P9 -> 21.5 | N9: 21 | P9: 0.5
B10: 9 | D10: 46203 | E10: Giugno | F10: STI | G10: =M10*$T$8 -> 4000 | H10: 0 | I10: =IF(L10="x",0,0.04*(J10+G10)) -> 160.08 | J10: 2 | K10: =G10+I10+J10 -> 4162.08 | M10: =N10-O10+P10 -> 20 | N10: 20
B11: 10 | D11: 46234 | E11: Luglio | F11: STI | G11: =M11*$T$8 -> 4700 | H11: 0 | I11: =IF(L11="x",0,0.04*(J11+G11)) -> 188.08 | J11: 2 | K11: =G11+I11+J11 -> 4890.08 | M11: =N11-O11+P11 -> 23.5 | N11: 23 | P11: 0.5 | S11: Coefficiente ATECO | T11: 0.78
B12: 11 | D12: 46265 | E12: Agosto | F12: STI | G12: =M12*$T$8 -> 2000 | H12: 0 | I12: =IF(L12="x",0,0.04*(J12+G12)) -> 80.08 | J12: 2 | K12: =G12+I12+J12 -> 2082.08 | M12: =N12-O12+P12 -> 10 | N12: 20 | O12: 10 | T12: forfettario
B13: 12 | D13: 46295 | E13: Settembre | F13: STI | G13: =M13*$T$8 -> 4500 | H13: 0 | I13: =IF(L13="x",0,0.04*(J13+G13)) -> 180.08 | J13: 2 | K13: =G13+I13+J13 -> 4682.08 | M13: =N13-O13+P13 -> 22.5 | N13: 22 | P13: 0.5 | S13: Totale fatturato annuo | T13: =G21 -> 45590
B14: 13 | D14: 46326 | E14: Ottobre | F14: STI | G14: =M14*$T$8 -> 4600 | H14: 0 | I14: =IF(L14="x",0,0.04*(J14+G14)) -> 184.08 | J14: 2 | K14: =G14+I14+J14 -> 4786.08 | M14: =N14-O14+P14 -> 23 | N14: 23 | S14: volume d'affari compessivo | T14: =T13+SUM(J4:J19) -> 45616
B15: 14 | D15: 46356 | E15: Novembre | F15: STI | G15: =M15*$T$8 -> 4100 | H15: 0 | I15: =IF(L15="x",0,0.04*(J15+G15)) -> 164.08 | J15: 2 | K15: =G15+I15+J15 -> 4266.08 | M15: =N15-O15+P15 -> 20.5 | N15: 20 | P15: 0.5 | S15: Spese deducibili
B16: 15 | F16: Cigliani | I16: =IF(L16="x",0,0.04*(J16+G16)) -> 0.08 | J16: 2 | K16: =G16+I16+J16 -> 2.08 | S16: Imponibile | T16: =0.78*T14 -> 35580.48
S19: Imposta sostitutiva (15% al fisco) | T19: =0.15*(T16-T26) -> 4278.7006 | V19: Già pagato | W19: Da pagare
F20: totale fatturato | G20: =SUBTOTAL(9,G4:G19) -> 45590 | I20: =SUBTOTAL(9,I4:I19) -> 1824.64 | J20: TOT | K20: =SUBTOTAL(9,K4:K19) -> 47440.64 | M20: =SUM(M4:M15) -> 240 | N20: =SUM(N4:N15) -> 251
F21: totale incassato | G21: =SUM(G4:G19) -> 45590 | M21: =SUM(M4:M15) -> 240
S22: INARCASSA | V22: Già pagato | W22: Da pagare
S23: Contributo soggettivo | T23: =MAX(780,0.0725*T16)*IF(U26="Sì",1,2) -> 5159.1696
S24: Contributo integrativo | T24: =MAX(231.5,I20) -> 1824.64
S25: Contributo maternità | T25: 72 | U25: Ridotto
M26: Tasse ad oggi | O26: =(T19+T26)*SUM(K4:K9)/K20-V26+'2024 reale'!U25 -> 5392.4211 | T26: =SUM(T23:T25) -> 7055.8096 | U26: No | V26: =SUM(V23:V25) -> 0 | W26: =SUM(W23:W25) -> 0
T28: =(K20-T29)/K20 -> 0.23891984 | V28: =1-(G20-T19-T23-T25)/G20 -> 0.20859553
S29: Netto totale | T29: =K20-T19-T26 -> 36106.13
S31: Netto mensile anno attuale | T31: =T29/12 -> 3008.8442 | W31: Rimanente 2026 | X31: =W26+W20 -> 0 | Y31: =SUMIFS(K4:K15,D4:D15,"<"&TODAY())/K20*(T19+T26)-V26-V20 -> 6386.8434
S32: Netto mensile 13 mensilità | T32: =T31/13*12 -> 2777.3946 | W32: Anno precedente | X32: ='2024 reale'!U19+'2024 reale'!U25 -> -0.01885 | Y32: =X32+Y31 -> 6386.8246

Sheet 2028 bozza
C1: ELENCO FATTURE
C2: Anno 2025 | H2: Anno 2017
B3: Numero | C3: Emessa? | D3: Girorno emissione | E3: Mese | F3: Destinatario | G3: Netto | H3: Iva | I3: Integr. 4% | J3: Bollo | K3: Totale | L3: Estero? | M3: Lavorati reali | N3: Giorni lavorativi | O3: Ferie / malattia | P3: Extra week | Q3: Spostati dal mese precedente
B4: 17 | D4: 46022 | E4: Dicembre | F4: STI | G4: =M4*$T$7 -> 3200 | H4: 0 | I4: =IF(L4="x",0,0.04*(J4+G4)) -> 128.08 | J4: 2 | K4: =G4+I4+J4 -> 3330.08 | M4: =N4-O4+P4 -> 16 | N4: 20 | O4: 4 | Q4: 0.5 | R4: da novembre
B5: 1 | D5: 46053 | E5: Gennaio | F5: STI | G5: =M5*$T$7 -> 4200 | H5: 0 | I5: =IF(L5="x",0,0.04*(J5+G5)) -> 168.08 | J5: 2 | K5: =G5+I5+J5 -> 4370.08 | M5: =N5-O5+P5 -> 21 | N5: 21
B6: 2 | D6: 46081 | E6: Febbraio | F6: STI | G6: =M6*$T$7 -> 4100 | H6: 0 | I6: =IF(L6="x",0,0.04*(J6+G6)) -> 164.08 | J6: 2 | K6: =G6+I6+J6 -> 4266.08 | M6: =N6-O6+P6 -> 20.5 | N6: 20 | P6: 0.5
B7: 4 | D7: 46112 | E7: Marzo | F7: STI | G7: =M7*$T$7 -> 4300 | H7: 0 | I7: =IF(L7="x",0,0.04*(J7+G7)) -> 172.08 | J7: 2 | K7: =G7+I7+J7 -> 4474.08 | M7: =N7-O7+P7 -> 21.5 | N7: 21 | P7: 0.5 | S7: Prezzo giornaliero | T7: 200
B8: 5 | D8: 46142 | E8: Aprile | F8: STI | G8: =M8*$T$7 -> 4000 | H8: 0 | I8: =IF(L8="x",0,0.04*(J8+G8)) -> 160.08 | J8: 2 | K8: =G8+I8+J8 -> 4162.08 | M8: =N8-O8+P8 -> 20 | N8: 20 | S8: Prezzo giornaliero dal 01/06 | T8: 200
B9: 7 | D9: 46173 | E9: Maggio | F9: STI | G9: =M9*$T$7 -> 4300 | H9: 0 | I9: =IF(L9="x",0,0.04*(J9+G9)) -> 172.08 | J9: 2 | K9: =G9+I9+J9 -> 4474.08 | M9: =N9-O9+P9 -> 21.5 | N9: 21 | P9: 0.5
B10: 9 | D10: 46203 | E10: Giugno | F10: STI | G10: =M10*$T$8 -> 4000 | H10: 0 | I10: =IF(L10="x",0,0.04*(J10+G10)) -> 160.08 | J10: 2 | K10: =G10+I10+J10 -> 4162.08 | M10: =N10-O10+P10 -> 20 | N10: 20
B11: 10 | D11: 46234 | E11: Luglio | F11: STI | G11: =M11*$T$8 -> 4700 | H11: 0 | I11: =IF(L11="x",0,0.04*(J11+G11)) -> 188.08 | J11: 2 | K11: =G11+I11+J11 -> 4890.08 | M11: =N11-O11+P11 -> 23.5 | N11: 23 | P11: 0.5 | S11: Coefficiente ATECO | T11: 0.78
B12: 11 | D12: 46265 | E12: Agosto | F12: STI | G12: =M12*$T$8 -> 2000 | H12: 0 | I12: =IF(L12="x",0,0.04*(J12+G12)) -> 80.08 | J12: 2 | K12: =G12+I12+J12 -> 2082.08 | M12: =N12-O12+P12 -> 10 | N12: 20 | O12: 10 | T12: forfettario
B13: 12 | D13: 46295 | E13: Settembre | F13: STI | G13: =M13*$T$8 -> 4500 | H13: 0 | I13: =IF(L13="x",0,0.04*(J13+G13)) -> 180.08 | J13: 2 | K13: =G13+I13+J13 -> 4682.08 | M13: =N13-O13+P13 -> 22.5 | N13: 22 | P13: 0.5 | S13: Totale fatturato annuo | T13: =G21 -> 48000
B14: 13 | D14: 46326 | E14: Ottobre | F14: STI | G14: =M14*$T$8 -> 4600 | H14: 0 | I14: =IF(L14="x",0,0.04*(J14+G14)) -> 184.08 | J14: 2 | K14: =G14+I14+J14 -> 4786.08 | M14: =N14-O14+P14 -> 23 | N14: 23 | S14: volume d'affari compessivo | T14: =T13+SUM(J4:J19) -> 48026
B15: 14 | D15: 46356 | E15: Novembre | F15: STI | G15: =M15*$T$8 -> 4100 | H15: 0 | I15: =IF(L15="x",0,0.04*(J15+G15)) -> 164.08 | J15: 2 | K15: =G15+I15+J15 -> 4266.08 | M15: =N15-O15+P15 -> 20.5 | N15: 20 | P15: 0.5 | S15: Spese deducibili
B16: 15 | F16: Cigliani | I16: =IF(L16="x",0,0.04*(J16+G16)) -> 0.08 | J16: 2 | K16: =G16+I16+J16 -> 2.08 | S16: Imponibile | T16: =0.78*T14 -> 37460.28
S19: Imposta sostitutiva (15% al fisco) | T19: =0.15*(T16-T26) -> 4505.3249 | V19: Già pagato | W19: Da pagare
F20: totale fatturato | G20: =SUBTOTAL(9,G4:G19) -> 48000 | I20: =SUBTOTAL(9,I4:I19) -> 1921.04 | J20: TOT | K20: =SUBTOTAL(9,K4:K19) -> 49947.04 | M20: =SUM(M4:M15) -> 240 | N20: =SUM(N4:N15) -> 251
F21: totale incassato | G21: =SUM(G4:G19) -> 48000 | M21: =SUM(M4:M15) -> 240
S22: INARCASSA | V22: Già pagato | W22: Da pagare
S23: Contributo soggettivo | T23: =MAX(780,0.0725*T16)*IF(U26="Sì",1,2) -> 5431.7406
S24: Contributo integrativo | T24: =MAX(231.5,I20) -> 1921.04
S25: Contributo maternità | T25: 72 | U25: Ridotto
M26: Tasse ad oggi | O26: =(T19+T26)*SUM(K4:K9)/K20-V26+'2024 reale'!U25 -> 5989.6264 | T26: =SUM(T23:T25) -> 7424.7806 | U26: No | V26: =SUM(V23:V25) -> 0 | W26: =SUM(W23:W25) -> 0
T28: =(K20-T29)/K20 -> 0.23885511 | V28: =1-(G20-T19-T23-T25)/G20 -> 0.2085222
S29: Netto totale | T29: =K20-T19-T26 -> 38016.934
S31: Netto mensile anno attuale | T31: =T29/12 -> 3168.0779 | W31: Rimanente 2026 | X31: =W26+W20 -> 0 | Y31: =SUMIFS(K4:K15,D4:D15,"<"&TODAY())/K20*(T19+T26)-V26-V20 -> 6983.7793
S32: Netto mensile 13 mensilità | T32: =T31/13*12 -> 2924.3796 | W32: Anno precedente | X32: ='2024 reale'!U19+'2024 reale'!U25 -> -0.01885 | Y32: =X32+Y31 -> 6983.7605

Sheet Studi
C1: ELENCO FATTURE
C2: Anno 2025 | H2: Anno 2017
B3: Numero | C3: Emessa? | D3: Girorno emissione | E3: Mese | F3: Destinatario | G3: Netto | H3: Iva | I3: Integr. 4% | J3: Bollo | K3: Totale | L3: Estero? | M3: Lavorati reali | N3: Giorni lavorativi | O3: Ferie / malattia | P3: Extra week
B4: 17 | C4: x | D4: 45657 | E4: Dicembre | F4: STI | G4: 4000 | H4: 0 | I4: =IF(L4="x",0,0.04*(J4+G4)) -> 160.08 | J4: 2 | K4: =G4+I4+J4 -> 4162.08 | M4: =N4-O4+P4 -> 15 | N4: 20 | O4: 5
B5: 1 | C5: x | D5: 45688 | E5: Gennaio | F5: STI | G5: 4000 | H5: 0 | I5: =IF(L5="x",0,0.04*(J5+G5)) -> 160.08 | J5: 2 | K5: =G5+I5+J5 -> 4162.08 | M5: =N5-O5+P5 -> 21 | N5: 21
B6: 2 | C6: x | D6: 45716 | E6: Febbraio | F6: STI | G6: 4000 | H6: 0 | I6: =IF(L6="x",0,0.04*(J6+G6)) -> 160.08 | J6: 2 | K6: =G6+I6+J6 -> 4162.08 | M6: =N6-O6+P6 -> 20 | N6: 20
B7: 4 | C7: x | D7: 45747 | E7: Marzo | F7: STI | G7: 4000 | H7: 0 | I7: =IF(L7="x",0,0.04*(J7+G7)) -> 160.08 | J7: 2 | K7: =G7+I7+J7 -> 4162.08 | M7: =N7-O7+P7 -> 21 | N7: 21 | R7: Prezzo giornaliero | S7: 165
B8: 5 | C8: x | D8: 45777 | E8: Aprile | F8: STI | G8: 4000 | H8: 0 | I8: =IF(L8="x",0,0.04*(J8+G8)) -> 160.08 | J8: 2 | K8: =G8+I8+J8 -> 4162.08 | M8: =N8-O8+P8 -> 20 | N8: 20
B9: 7 | C9: x | D9: 45808 | E9: Maggio | F9: STI | G9: 4000 | H9: 0 | I9: =IF(L9="x",0,0.04*(J9+G9)) -> 160.08 | J9: 2 | K9: =G9+I9+J9 -> 4162.08 | M9: =N9-O9+P9 -> 17 | N9: 21 | O9: 4
B10: 9 | D10: 45838 | E10: Giugno | F10: STI | G10: 4000 | H10: 0 | I10: =IF(L10="x",0,0.04*(J10+G10)) -> 160.08 | J10: 2 | K10: =G10+I10+J10 -> 4162.08 | M10: =N10-O10+P10 -> 20 | N10: 20
B11: 10 | D11: 45869 | E11: Luglio | F11: STI | G11: 4000 | H11: 0 | I11: =IF(L11="x",0,0.04*(J11+G11)) -> 160.08 | J11: 2 | K11: =G11+I11+J11 -> 4162.08 | M11: =N11-O11+P11 -> 23 | N11: 23 | R11: Coefficiente ATECO | S11: 0.78
B12: 11 | D12: 45900 | E12: Agosto | F12: STI | G12: 4000 | H12: 0 | I12: =IF(L12="x",0,0.04*(J12+G12)) -> 160.08 | J12: 2 | K12: =G12+I12+J12 -> 4162.08 | M12: =N12-O12+P12 -> 10 | N12: 20 | O12: 10 | S12: forfettario
B13: 12 | D13: 45930 | E13: Settembre | F13: STI | G13: 4000 | H13: 0 | I13: =IF(L13="x",0,0.04*(J13+G13)) -> 160.08 | J13: 2 | K13: =G13+I13+J13 -> 4162.08 | M13: =N13-O13+P13 -> 22 | N13: 22 | R13: Totale fatturato annuo | S13: =G21 -> 48000
B14: 13 | D14: 45961 | E14: Ottobre | F14: STI | G14: 4000 | H14: 0 | I14: =IF(L14="x",0,0.04*(J14+G14)) -> 160.08 | J14: 2 | K14: =G14+I14+J14 -> 4162.08 | M14: =N14-O14+P14 -> 23 | N14: 23 | Q14: 0,5 sono dal mese precedente | R14: volume d'affari compessivo | S14: =S13+SUM(J4:J19) -> 48024
B15: 14 | D15: 45991 | E15: Novembre | F15: STI | G15: 4000 | H15: 0 | I15: =IF(L15="x",0,0.04*(J15+G15)) -> 160.08 | J15: 2 | K15: =G15+I15+J15 -> 4162.08 | M15: =N15-O15+P15 -> 19 | N15: 20 | O15: 1 | R15: Spese deducibili
R16: Imponibile | S16: =0.78*S14 -> 37458.72
R17: Imposta sostitutiva (15% al fisco) | S17: =0.15*(S16-S24) -> 4505.1368 | U17: Già pagato | V17: Da pagare
V18: 0
T19: LIMITE
F20: totale fatturato | G20: =SUBTOTAL(9,G4:G19) -> 48000 | I20: =SUBTOTAL(9,I4:I19) -> 1920.96 | J20: TOT | K20: =SUBTOTAL(9,K4:K19) -> 49944.96 | M20: =SUM(M4:M15) -> 231 | N20: =SUM(N4:N15) -> 251 | O20: =SUM(O4:O15) -> 20 | R20: INARCASSA | T20: 39000 | U20: Già pagato | V20: Da pagare
F21: totale incassato | G21: =SUM(G4:G19) -> 48000 | M21: Obiettivo 120! | R21: Contributo soggettivo | S21: =MAX(780,0.0725*S16)*IF(T24="Sì",1,2) -> 5431.5144 | T21: Extra | U21: 633.5 | V21: =S21-U21 -> 4798.0144
R22: Contributo integrativo | S22: =MAX(231.5,I20) -> 1920.96 | T22: =(T20-S16)/0.78 -> 1976 | V22: =S22-U22 -> 1920.96
R23: Contributo maternità | S23: 72 | T23: Ridotto | V23: =S23-U23 -> 72
S24: =SUM(S21:S23) -> 7424.4744 | T24: No | U24: =SUM(U21:U23) -> 633.5 | V24: =SUM(V21:V23) -> 6790.9744
M26: Tasse ad oggi | O26: =(S17+S24)*SUM(K4:K9)/K20-U24+'2024 reale'!U25 -> 5331.2868 | S26: =(K20-S27)/K20 -> 0.23885516 | U26: =1-(G20-S17-S21-S23)/G20 -> 0.20851357
R27: Netto totale | S27: =K20-S17-S24 -> 38015.349
R29: Netto mensile anno attuale | S29: =S27/12 -> 3167.9457 | V29: Rimanente 2024 | W29: =V24+V18 -> 6790.9744 | X29: =SUMIFS(K4:K15,D4:D15,"<"&TODAY())/K20*(S17+S24)-U24-U18 -> 11296.111
R30: Netto mensile 13 mensilità | S30: =S29/13*12 -> 2924.2576 | V30: Anno precedente | W30: ='2023 reale'!T31 -> 0 | X30: =W30+X29 -> 11296.111
R32: A1 | S32: =S33*0.78*0+26639 -> 26639 | T32: preso dal commericalista LM22 colonna 5
R33: B1 | S33: =(SUM(G4:G24)+SUM(J4:J24))*0+34152 -> 34152 | T33: preso dal commericalista LM22 colonna 3
R34: B2.1 | S34: =SUMIFS(G4:G19,L4:L19,T34)+SUMIFS(J4:J19,L4:L19,T34) -> 48024 | T34: =""
R35: B5.1 | S35: =SUMIFS(G4:G19,L4:L19,T35)+SUMIFS(J4:J19,L4:L19,T35) -> 0 | T35: x | U35: CHECK!
R36: B7.1 | S36: =S34 -> 48024 | U36: =S33-S34-S35 -> -13872 | V36: <1€
R37: E1 | S37: =I21 -> 0

Sheet Studio
C1: ELENCO FATTURE
C2: Anno 2023 | J2: Anno 2017
B4: Numero | C4: NOTE | E4: Mese | G4: Data emissione | H4: Destinatario | I4: Netto | J4: Iva | K4: Integr. 4% | L4: Bollo | M4: Totale | N4: Estero
B5: 13 | D5: 45657 | E5: Dicembre | H5: STI | I5: 4500 | J5: 0 | K5: =IF(N5="x",0,0.04*(L5+I5)) -> 180.08 | L5: 2 | M5: =I5+K5+L5 -> 4682.08 | O5: =M5*(1-Q27) -> 3564.3782 | P5: =O5-M5 -> -1117.7018
B6: 1 | D6: 45322 | E6: Gennaio | F6: =IF(#REF!="CASA",CONCATENATE("C:\Users\studi\Google Drive\CONTABILITA'\",D6,"\",E6," Trimestre\Fatture\",C6,".pdf"),CONCATENATE("C:\Users\Sebastiano\Google Drive\CONTABILITA'\",D6,"\",E6," Trimestre\Fatture\",C6,".pdf")) -> #REF! | H6: STI | I6: 4500 | J6: 0 | K6: =IF(N6="x",0,0.04*(L6+I6)) -> 180.08 | L6: 2 | M6: =I6+K6+L6 -> 4682.08
B7: 2 | D7: 45351 | E7: Febbraio | F7: =IF(#REF!="CASA",CONCATENATE("C:\Users\studi\Google Drive\CONTABILITA'\2019\",E7," Trimestre\Fatture\",C7,".pdf"),CONCATENATE("C:\Users\Sebastiano\Google Drive\CONTABILITA'\2019\",E7," Trimestre\Fatture\",C7,".pdf")) -> #REF! | H7: STI | I7: 4500 | J7: 0 | K7: =IF(N7="x",0,0.04*(L7+I7)) -> 180.08 | L7: 2 | M7: =I7+K7+L7 -> 4682.08
B8: 3 | D8: 45382 | E8: Marzo | F8: =IF(#REF!="CASA",CONCATENATE("C:\Users\studi\Google Drive\CONTABILITA'\2020\",E8," Trimestre\Fatture\",C8,".pdf"),CONCATENATE("C:\Users\Sebastiano\Google Drive\CONTABILITA'\2020\",E8," Trimestre\Fatture\",C8,".pdf")) -> #REF! | H8: STI | I8: 4500 | J8: 0 | K8: =IF(N8="x",0,0.04*(L8+I8)) -> 180.08 | L8: 2 | M8: =I8+K8+L8 -> 4682.08
B9: 4 | D9: 45412 | E9: Aprile | H9: STI | I9: 4500 | J9: 0 | K9: =IF(N9="x",0,0.04*(L9+I9)) -> 180.08 | L9: 2 | M9: =I9+K9+L9 -> 4682.08
B10: 5 | D10: 45443 | E10: Maggio | F10: =IF(#REF!="CASA",CONCATENATE("C:\Users\studi\Google Drive\CONTABILITA'\2020\Fatture\",E10," Trimestre\",C10,".pdf"),CONCATENATE("C:\Users\Sebastiano\Google Drive\CONTABILITA'\2020\Fatture\",E10," Trimestre\",C10,".pdf")) -> #REF! | H10: STI | I10: 4500 | J10: 0 | K10: =IF(N10="x",0,0.04*(L10+I10)) -> 180.08 | L10: 2 | M10: =I10+K10+L10 -> 4682.08 | S10: =55+1.3+2.9+0.35+2+0.7+5-2.15 -> 65.1
B11: 6 | D11: 45473 | E11: Giugno | F11: =IF(#REF!="CASA",CONCATENATE("C:\Users\studi\Google Drive\CONTABILITA'\2020\Fatture\",E11," Trimestre\",C11,".pdf"),CONCATENATE("C:\Users\Sebastiano\Google Drive\CONTABILITA'\2020\Fatture\",E11," Trimestre\",C11,".pdf")) -> #REF! | H11: STI | I11: 4500 | J11: 0 | K11: =IF(N11="x",0,0.04*(L11+I11)) -> 180.08 | L11: 2 | M11: =I11+K11+L11 -> 4682.08
B12: 7 | D12: 45504 | E12: Luglio | F12: =IF(#REF!="CASA",CONCATENATE("C:\Users\studi\Google Drive\CONTABILITA'\2020\Fatture\",E12," Trimestre\",C12,".pdf"),CONCATENATE("C:\Users\Sebastiano\Google Drive\CONTABILITA'\2020\Fatture\",E12," Trimestre\",C12,".pdf")) -> #REF! | H12: STI | I12: 4500 | J12: 0 | K12: =IF(N12="x",0,0.04*(L12+I12)) -> 180.08 | L12: 2 | M12: =I12+K12+L12 -> 4682.08 | O12: =M12-M11 -> 0 | Q12: Coefficiente ATECO | S12: 0.78
B13: 8 | D13: 45535 | E13: Agosto | F13: =IF(#REF!="CASA",CONCATENATE("C:\Users\studi\Google Drive\CONTABILITA'\2020\Fatture\",E13," Trimestre\",C13,".pdf"),CONCATENATE("C:\Users\Sebastiano\Google Drive\CONTABILITA'\2020\Fatture\",E13," Trimestre\",C13,".pdf")) -> #REF! | H13: STI | I13: 4500 | J13: 0 | K13: =IF(N13="x",0,0.04*(L13+I13)) -> 180.08 | L13: 2 | M13: =I13+K13+L13 -> 4682.08
B14: 9 | D14: 45565 | E14: Settembre | F14: =IF(#REF!="CASA",CONCATENATE("C:\Users\studi\Google Drive\CONTABILITA'\2020\Fatture\",E14," Trimestre\",C14,".pdf"),CONCATENATE("C:\Users\Sebastiano\Google Drive\CONTABILITA'\2020\Fatture\",E14," Trimestre\",C14,".pdf")) -> #REF! | H14: STI | I14: 4500 | J14: 0 | K14: =IF(N14="x",0,0.04*(L14+I14)) -> 180.08 | L14: 2 | M14: =I14+K14+L14 -> 4682.08 | Q14: forfettario
B15: 10 | D15: 45596 | E15: Ottobre | F15: =IF(#REF!="CASA",CONCATENATE("C:\Users\studi\Google Drive\CONTABILITA'\2020\Fatture\",E15," Trimestre\",C15,".pdf"),CONCATENATE("C:\Users\Sebastiano\Google Drive\CONTABILITA'\2020\Fatture\",E15," Trimestre\",C15,".pdf")) -> #REF! | H15: STI | I15: 4500 | J15: 0 | K15: =IF(N15="x",0,0.04*(L15+I15)) -> 180.08 | L15: 2 | M15: =I15+K15+L15 -> 4682.08 | P15: Totale fatturato annuo | Q15: =I26 -> 54000
B16: 11 | D16: 45626 | E16: Novembre | F16: =IF(#REF!="CASA",CONCATENATE("C:\Users\studi\Google Drive\CONTABILITA'\2020\Fatture\",E16," Trimestre\",C16,".pdf"),CONCATENATE("C:\Users\Sebastiano\Google Drive\CONTABILITA'\2020\Fatture\",E16," Trimestre\",C16,".pdf")) -> #REF! | H16: STI | I16: 4500 | J16: 0 | K16: =IF(N16="x",0,0.04*(L16+I16)) -> 180.08 | L16: 2 | M16: =I16+K16+L16 -> 4682.08 | P16: volume d'affari compessivo | Q16: =Q15+SUM(L5:L24) -> 54024
P17: Spese deducibili
P18: Imponibile | Q18: =0.78*Q16 -> 42138.72
P19: Imposta sostitutiva (15% al fisco) | Q19: =0.15*(Q18-Q25) -> 5069.3468
P21: INARCASSA
P22: Contributo soggettivo | Q22: =MAX(780,0.0725*Q18)*IF(S22="Sì",1,2) -> 6110.1144
P23: Contributo integrativo | Q23: =MAX(231.5,K25) -> 2160.96
P24: Contributo maternità | Q24: 72
H25: totale fatturato | I25: =SUBTOTAL(9,I5:I24) -> 54000 | K25: =SUBTOTAL(9,K5:K24) -> 2160.96 | L25: TOT | M25: =SUBTOTAL(9,M5:M24) -> 56184.96 | Q25: =SUM(Q22:Q24) -> 8343.0744
H26: totale incassato | I26: =SUM(I5:I24) -> 54000
Q27: =(M25-Q28)/M25 -> 0.23871907 | S27: =1-(I25-Q19-Q22-Q24)/I25 -> 0.20836039
P28: Netto totale | Q28: =M25-Q19-Q25 -> 42772.539
P30: Netto mensile anno attuale | Q30: =Q28/12 -> 3564.3782
P31: Netto mensile 13 mensilità | Q31: =Q30/13*12 -> 3290.1953
P32: Netto mensile 15 mensilità | Q32: =Q30/15*12 -> 2851.5026
G33: A1 | H33: =H34*0.78*0+26639 -> 26639 | I33: preso dal commericalista LM22 colonna 5
G34: B1 | H34: =(SUM(I5:I29)+SUM(L5:L29))*0+34152 -> 34152 | I34: preso dal commericalista LM22 colonna 3 | N34: Anno | O34: STI | R34: TOP | U34: Proposto
O35: €/mese | P35: €/giorno | Q35: Netto mese 13 | Z35: €/h
G36: B2.1 | H36: =SUMIFS(I5:I24,N5:N24,I36)+SUMIFS(L5:L24,N5:N24,I36) -> 54024 | I36: ="" | N36: Partenza | O36: 2900 | P36: =O36*12/240 -> 145 | R36: 2900 | S36: =R36*12/1784*8 -> 156.05381 | T36: 2119 | U36: 2900 | V36: =U36*12/1784*8 -> 156.05381 | W36: 2120 | Y36: =U36*1.04*12 -> 36192 | Z36: =W36*13/1784 -> 15.44843
G37: B5.1 | H37: =SUMIFS(I5:I24,N5:N24,I37)+SUMIFS(L5:L24,N5:N24,I37) -> 0 | I37: x | J37: CHECK! | N37: 2025 | O37: =O36*1.1 -> 3190 | P37: =O37/240*12 -> 159.5 | Q37: 2332 | R37: =S37*240/12 -> 3433.1839 | S37: =S36*1.1 -> 171.65919 | T37: 2510 | U37: =V37*240/12 -> 3300 | V37: 165 | W37: 2412 | X37: =Y37/$Y$36 -> 1.137931 | Y37: =U37*1.04*12 -> 41184 | Z37: =W37*13/240/8 -> 16.33125
G38: B7.1 | H38: =H36 -> 54024 | J38: =H34-H36-H37 -> -19872 | K38: <1€ | N38: 2026 | O38: =O37*1.1 -> 3509 | P38: =O38/240*12 -> 175.45 | Q38: 2565 | R38: =S38*240/12 -> 3745.2915 | S38: =S36*1.2 -> 187.26457 | T38: 2738 | U38: =V38*240/12 -> 3600 | V38: =V37*1.1*0+180 -> 180 | W38: 2632 | X38: =Y38/$Y$36 -> 1.2413793 | Y38: =U38*1.04*12 -> 44928 | Z38: =W38*13/240/8 -> 17.820833
G39: E1 | H39: =K26 -> 0 | N39: 2027 | O39: =O38*1.1 -> 3859.9 | P39: =O39/240*12 -> 192.995 | Q39: 2822 | R39: =S39*240/12 -> 4057.3991 | S39: =S36*1.3 -> 202.86996 | T39: 2970 | U39: =V39*240/12 -> 4000 | V39: =V38*1.1*0+200 -> 200 | W39: 2925 | X39: =Y39/$Y$36 -> 1.3793103 | Y39: =U39*1.04*12 -> 49920 | Z39: =W39*13/240/8 -> 19.804688
M40: =O39/O36 -> 1.331
N41: prop

Sheet Reddito medio inar
B3: Anno
B4: 2020 | C4: 27425 | D4: 2023 | E4: =(C4+C5)/2 -> 31704
B5: 2021 | C5: 35983 | D5: 2024 | E5: =(C5+C6)/2 -> 39652.5 | F5: =C5/C4 -> 1.312051
B6: 2022 | C6: 43322 | F6: =C6/C5 -> 1.2039574
B7: 2023
B17: Dal 01/01/2021 il beneficio della riduzione contributiva, anche se già riconosciuto per gli anni precedenti, spetta solo ai giovani associati che dichiarino un reddito professionale IRPEF inferiore o uguale al reddito medio dichiarato dagli iscritti a Inarcassa nel biennio precedente all’anno oggetto di agevolazione. Ad esempio, per l’anno 2023 il reddito medio di riferimento è quello dichiarato dagli iscritti nel 2022 (reddito 2021) e 2021 (reddito 2020) pari a euro 31.704,00.

Sheet Analisi complessiva lavoro
B2: Anno | F2: Extra | G2: Spesa extra | H2: Tassazione media | I2: Netto mensile 12 | J2: Netto mensile 13
B3: 2020 | C3: Lavoro principale | D3: =E3+E4 -> 7237 | E3: =SUM('2021 reale'!X5:X6) -> 7237 | F3: 5000 | H3: ='2021 reale'!U28 -> 0.23112448 | I3: =(E3*(1-H3)+F3*0.8)/8 -> 1195.544 | J3: =I3*12/13 -> 1103.5791
C4: Lavoro secondario
B5: 2021 | C5: Lavoro principale | D5: =E5+E6 -> 30785 | E5: =SUM('2021 reale'!L5:L17)-SUM('2021 reale'!X5:X6) -> 26035 | G5: 1100 | H5: ='2021 reale'!U28 -> 0.23112448 | I5: =((E5+E6)*(1-H5)+F5+F6-G5-G6)/12 -> 1880.8194 | J5: =I5*12/13 -> 1736.141 | K5: =I5*12 -> 22569.833
C6: Lavoro secondario | E6: =SUM('2021 reale'!L18:L19) -> 4750
B7: 2022 | C7: Lavoro principale | D7: =E7+E8 -> 32198.07 | E7: =SUM('2022 reale'!I5:I21)-'2022 reale'!I13 -> 31798.07 | G7: 1100 | H7: ='2022 reale'!R32 -> 0.15466999 | I7: =((E7+E8)*(1-H7)+F7+F8-G7-G8)/12 -> 2176.4996 | J7: =I7*12/13 -> 2009.0765 | K7: =I7*12 -> 26117.995
C8: Lavoro secondario | E8: ='2022 reale'!I13 -> 400
B9: 2023 | C9: Lavoro principale | D9: =E9+E10 -> 34126.01 | E9: =SUM('2023 reale'!I5:I17)-'2023 reale'!I7 -> 33226.01 | G9: 1200 | H9: ='2023 reale'!R28 -> 0.1642783 | I9: =((E9+E10)*(1-H9)+F9+F10-G9-G10)/12 -> 2343.3206 | J9: =I9*12/13 -> 2163.0652 | K9: =I9*12 -> 28119.847
C10: Lavoro secondario | E10: ='2023 reale'!I7 -> 900 | F10: 800
B11: 2024 | C11: Lavoro principale | D11: =E11+E12 -> 42497 | E11: =SUM('2024 reale'!I5:I22)-E12 -> 34919 | G11: 1200 | H11: ='2024 reale'!S27 -> 0.15041248 | I11: =((E11+E12)*(1-H11)+F11+F12-G11-G12)/12 -> 3000.4101 | J11: =I11*12/13 -> 2769.6093 | K11: =I11*12 -> 36004.921
C12: Lavoro secondario | E12: ='2024 reale'!I9+'2024 reale'!I16+'2024 reale'!I17+'2024 reale'!I19+'2024 reale'!I21+'2024 reale'!I22 -> 7578 | F12: =400+700 -> 1100
B13: 2025 | C13: Lavoro principale | D13: =E13+E14 -> 43834.14 | E13: =SUM('2025 reale'!F4:F21)-'2025 reale'!F7-'2025 reale'!F10-'2025 reale'!F12-'2025 reale'!F18-'2025 reale'!F18-'2025 reale'!F21 -> 38688.14 | G13: 1200 | H13: ='2025 reale'!U28 -> 0.1607685 | I13: =((E13+E14)*(1-H13)+F13+F14-G13-G14)/12 -> 2965.5826 | J13: =I13*12/13 -> 2737.4609 | K13: =I13*12 -> 35586.991
C14: Lavoro secondario | E14: ='2025 reale'!F26-'Analisi complessiva lavoro'!E13 -> 5146
B15: 2026 | C15: Lavoro principale | D15: =E15+E16 -> 44487.5 | E15: =SUM('2026 reale'!G4:G19)-E16 -> 39487.5 | F15: =5000-2700 -> 2300 | G15: 1300 | H15: ='2026 reale'!V28 -> 0.20863172 | I15: =((E15+E16)*(1-H15)+F15+F16-G15-G16)/12 -> 3017.1663 | J15: =I15*12/13 -> 2785.0766 | K15: =I15*12 -> 36205.996
C16: Lavoro secondario | E16: ='2026 reale'!G8 -> 5000
B17: 2027 | C17: Lavoro principale | D17: =E17+E18 -> 45590 | E17: =SUM('2027 bozza'!G4:G19)-E18 -> 45590 | G17: 1200 | H17: ='2027 bozza'!V28 -> 0.20859553 | I17: =((E17+E18)*(1-H17)+F17+F18-G17-G18)/12 -> 2906.6775 | J17: =I17*12/13 -> 2683.0869 | K17: =I17*12 -> 34880.13
C18: Lavoro secondario | E18: 0
B19: 2028 | C19: Lavoro principale | D19: =E19+E20 -> 48000 | E19: =SUM('2028 bozza'!G4:G19)-E20 -> 48000 | G19: 1200 | H19: ='2028 bozza'!V28 -> 0.2085222 | I19: =((E19+E20)*(1-H19)+F19+F20-G19-G20)/12 -> 3065.9112 | J19: =I19*12/13 -> 2830.0719 | K19: =I19*12 -> 36790.934
C20: Lavoro secondario | E20: 0
B23: 1° SCAT 05/2025 | C23: Lavoro principale | D23: =E23+E24 -> 39600 | E23: =Studio!Y37/1.04 -> 39600 | G23: 1200 | H23: =Studio!S27 -> 0.20836039 | I23: =((E23+E24)*(1-H23)+F23+F24-G23-G24)/12 -> 2512.4107 | J23: =I23*12/13 -> 2319.1483 | K23: =I23*12 -> 30148.928
C24: Lavoro secondario
B25: 2° SCAT 05/2026 | C25: Lavoro principale | D25: =E25+E26 -> 43200 | E25: =Studio!Y38/1.04 -> 43200 | G25: 1200 | H25: =H23 -> 0.20836039 | I25: =((E25+E26)*(1-H25)+F25+F26-G25-G26)/12 -> 2749.9026 | J25: =I25*12/13 -> 2538.3716 | K25: =I25*12 -> 32998.831
C26: Lavoro secondario
B27: 3° SCAT 05/2026 | C27: Lavoro principale | D27: =E27+E28 -> 48000 | E27: =Studio!Y39/1.04 -> 48000 | G27: 1200 | H27: =H25 -> 0.20836039 | I27: =((E27+E28)*(1-H27)+F27+F28-G27-G28)/12 -> 3066.5584 | J27: =I27*12/13 -> 2830.6693 | K27: =I27*12 -> 36798.701
C28: Lavoro secondario
